{"info":{"year":"2023","version":"1","description":"Exported from roboflow.ai","contributor":"","url":"https://public.roboflow.ai/object-detection/undefined","date_created":"2023-02-05T04:51:39+00:00"},"licenses":[{"id":1,"url":"https://creativecommons.org/licenses/by/4.0/","name":"CC BY 4.0"}],"categories":[{"id":0,"name":"Sample","supercategory":"none"},{"id":1,"name":"Assisted Pull Up and Dip Machine","supercategory":"Sample"},{"id":2,"name":"Exercise Balls","supercategory":"Sample"},{"id":3,"name":"Kettlebell","supercategory":"Sample"},{"id":4,"name":"json","supercategory":"Sample"}],"images":[{"id":0,"license":1,"file_name":"20211226_130645_jpg.rf.03d1504cff31efe52e58931d848d3cea.jpg","height":416,"width":416,"date_captured":"2023-02-05T04:51:39+00:00"},{"id":1,"license":1,"file_name":"20211226_131239_jpg.rf.057887b79c2f2eb0ab7ede1fbcf3f8d1.jpg","height":416,"width":416,"date_captured":"2023-02-05T04:51:39+00:00"},{"id":2,"license":1,"file_name":"20211224_185933_jpg.rf.08690b6c03d99d57aa1397f08067ce4c.jpg","height":416,"width":416,"date_captured":"2023-02-05T04:51:39+00:00"},{"id":3,"license":1,"file_name":"20211224_181043_jpg.rf.08cadd9c79abcf77368d8c8e0c7cda7b.jpg","height":416,"width":416,"date_captured":"2023-02-05T04:51:39+00:00"},{"id":4,"license":1,"file_name":"20211224_185438_jpg.rf.090fcc1ae4c9d1ebd286eb6b9d44566f.jpg","height":416,"width":416,"date_captured":"2023-02-05T04:51:39+00:00"},{"id":5,"license":1,"file_name":"20211226_131215_jpg.rf.09d6266af33330283c499ca6e9e8eef6.jpg","height":416,"width":416,"date_captured":"2023-02-05T04:51:39+00:00"},{"id":6,"license":1,"file_name":"20211224_180322_jpg.rf.0c5a6b894f5ef1a454e2fe7486e78be3.jpg","height":416,"width":416,"date_captured":"2023-02-05T04:51:39+00:00"},{"id":7,"license":1,"file_name":"20211224_180735_jpg.rf.0d02c8619d35cccbf9abdc85210b9674.jpg","height":416,"width":416,"date_captured":"2023-02-05T04:51:39+00:00"},{"id":8,"license":1,"file_name":"20211224_181128_jpg.rf.0d3fcb4f7b810a6c57a02bf1864b61d3.jpg","height":416,"width":416,"date_captured":"2023-02-05T04:51:39+00:00"},{"id":9,"license":1,"file_name":"20211224_185454_jpg.rf.0ec952a8f2484ffb5ff0b3fba0e51ad6.jpg","height":416,"width":416,"date_captured":"2023-02-05T04:51:39+00:00"},{"id":10,"license":1,"file_name":"20211224_185450_jpg.rf.0f48d6b62ad2d6786cff37e970a34ec5.jpg","height":416,"width":416,"date_captured":"2023-02-05T04:51:39+00:00"},{"id":11,"license":1,"file_name":"20211224_185529_jpg.rf.1044d5cee11ddb31061f60de02b93f46.jpg","height":416,"width":416,"date_captured":"2023-02-05T04:51:39+00:00"},{"id":12,"license":1,"file_name":"20211224_190044_jpg.rf.10af4c6bf0413c0185a1eb6a8d1c059a.jpg","height":416,"width":416,"date_captured":"2023-02-05T04:51:39+00:00"},{"id":13,"license":1,"file_name":"20211224_190049_jpg.rf.10f6ff5bd04b68b1aec5166eae8ebcea.jpg","height":416,"width":416,"date_captured":"2023-02-05T04:51:39+00:00"},{"id":14,"license":1,"file_name":"20211224_180407_jpg.rf.1410238c2bdbe1306b3aaf686863203e.jpg","height":416,"width":416,"date_captured":"2023-02-05T04:51:39+00:00"},{"id":15,"license":1,"file_name":"20211226_131242_jpg.rf.142dcabc96b6c296bed4f1f64e6444f2.jpg","height":416,"width":416,"date_captured":"2023-02-05T04:51:39+00:00"},{"id":16,"license":1,"file_name":"20211224_181126_jpg.rf.162658be0dceaa9b8b68d100400cffff.jpg","height":416,"width":416,"date_captured":"2023-02-05T04:51:39+00:00"},{"id":17,"license":1,"file_name":"20211226_130633_jpg.rf.16a8fab2d7a40fedcda43b5993a9f008.jpg","height":416,"width":416,"date_captured":"2023-02-05T04:51:39+00:00"},{"id":18,"license":1,"file_name":"20211224_180916_jpg.rf.1b929fb8a7de3aeb0ff9f04539573ca6.jpg","height":416,"width":416,"date_captured":"2023-02-05T04:51:39+00:00"},{"id":19,"license":1,"file_name":"20211224_180410_jpg.rf.1a8cb34dc1091f83013e03de0b073ad0.jpg","height":416,"width":416,"date_captured":"2023-02-05T04:51:39+00:00"},{"id":20,"license":1,"file_name":"20211226_130611_jpg.rf.1bdbd94ec71d96f93f5f59dd512ead21.jpg","height":416,"width":416,"date_captured":"2023-02-05T04:51:39+00:00"},{"id":21,"license":1,"file_name":"20211224_180739_jpg.rf.1d6a3bebc59b2c418d33bc60c9e908dc.jpg","height":416,"width":416,"date_captured":"2023-02-05T04:51:39+00:00"},{"id":22,"license":1,"file_name":"20211226_130632_jpg.rf.1d822b0cfb0e9d4ec4dd7b9892c16651.jpg","height":416,"width":416,"date_captured":"2023-02-05T04:51:39+00:00"},{"id":23,"license":1,"file_name":"20211224_180858_jpg.rf.1e40a75ddfe3c72e07292cc511202da2.jpg","height":416,"width":416,"date_captured":"2023-02-05T04:51:39+00:00"},{"id":24,"license":1,"file_name":"20211224_181054_jpg.rf.22d5bb462114e0ad3fdd562a8992723f.jpg","height":416,"width":416,"date_captured":"2023-02-05T04:51:39+00:00"},{"id":25,"license":1,"file_name":"20211224_180440_jpg.rf.28da1658cde28e633659714b0db14918.jpg","height":416,"width":416,"date_captured":"2023-02-05T04:51:39+00:00"},{"id":26,"license":1,"file_name":"20211224_181056_jpg.rf.247021d3ffb6393b8eb3839324201c90.jpg","height":416,"width":416,"date_captured":"2023-02-05T04:51:39+00:00"},{"id":27,"license":1,"file_name":"20211224_185443_jpg.rf.2b25619e6d482c706bbd99c7645fa0cf.jpg","height":416,"width":416,"date_captured":"2023-02-05T04:51:39+00:00"},{"id":28,"license":1,"file_name":"20211224_180838_jpg.rf.244351322b6c3b6e7299a0488cc678bc.jpg","height":416,"width":416,"date_captured":"2023-02-05T04:51:39+00:00"},{"id":29,"license":1,"file_name":"20211226_131225_jpg.rf.2a319d7da4cb9a97cad669b74f195333.jpg","height":416,"width":416,"date_captured":"2023-02-05T04:51:39+00:00"},{"id":30,"license":1,"file_name":"20211226_130647_jpg.rf.2f648d22495ac70d1f918ad4aa6d4410.jpg","height":416,"width":416,"date_captured":"2023-02-05T04:51:39+00:00"},{"id":31,"license":1,"file_name":"20211224_190014_jpg.rf.324565c40afb0afbabe2a25dcf20d01c.jpg","height":416,"width":416,"date_captured":"2023-02-05T04:51:39+00:00"},{"id":32,"license":1,"file_name":"20211226_131222_jpg.rf.3378586a83fb3423db613b583a786ce1.jpg","height":416,"width":416,"date_captured":"2023-02-05T04:51:39+00:00"},{"id":33,"license":1,"file_name":"20211224_180721_jpg.rf.3516d46f09035a174290960ac04f1337.jpg","height":416,"width":416,"date_captured":"2023-02-05T04:51:39+00:00"},{"id":34,"license":1,"file_name":"20211224_185950_jpg.rf.36df3da77554d5e97682bdb84541ab10.jpg","height":416,"width":416,"date_captured":"2023-02-05T04:51:39+00:00"},{"id":35,"license":1,"file_name":"20211224_180341_jpg.rf.337d138c613997c8b399691a2dc085e7.jpg","height":416,"width":416,"date_captured":"2023-02-05T04:51:39+00:00"},{"id":36,"license":1,"file_name":"20211226_130637_jpg.rf.38a4dc03ec1e5d458d865c7dfabf684c.jpg","height":416,"width":416,"date_captured":"2023-02-05T04:51:39+00:00"},{"id":37,"license":1,"file_name":"20211226_130626_jpg.rf.39e0072ba4724bfefde260dff3e4eccc.jpg","height":416,"width":416,"date_captured":"2023-02-05T04:51:39+00:00"},{"id":38,"license":1,"file_name":"20211224_185927_jpg.rf.372fb5ac79a26b0d98b0736d7cb4ac11.jpg","height":416,"width":416,"date_captured":"2023-02-05T04:51:39+00:00"},{"id":39,"license":1,"file_name":"20211224_185520_jpg.rf.3a93961dc62bfedb6bded148e103c4df.jpg","height":416,"width":416,"date_captured":"2023-02-05T04:51:39+00:00"},{"id":40,"license":1,"file_name":"20211224_181053_jpg.rf.3c10554b4d1a6025e26250adb95440af.jpg","height":416,"width":416,"date_captured":"2023-02-05T04:51:39+00:00"},{"id":41,"license":1,"file_name":"20211226_130658_jpg.rf.3d5f8a32266542632f85959b1c08fd60.jpg","height":416,"width":416,"date_captured":"2023-02-05T04:51:39+00:00"},{"id":42,"license":1,"file_name":"20211226_131226_jpg.rf.3dd4f3880b536381cbf13709a54d6ceb.jpg","height":416,"width":416,"date_captured":"2023-02-05T04:51:39+00:00"},{"id":43,"license":1,"file_name":"20211224_185435_jpg.rf.3c2258149b8bd38f910efd820849a063.jpg","height":416,"width":416,"date_captured":"2023-02-05T04:51:39+00:00"},{"id":44,"license":1,"file_name":"20211226_131244_jpg.rf.3fbeba5ff93d80421f532c3e1607d5cb.jpg","height":416,"width":416,"date_captured":"2023-02-05T04:51:39+00:00"},{"id":45,"license":1,"file_name":"20211224_181104_jpg.rf.41d0fe6c8cf2df36c1ac3ce3ebe0e244.jpg","height":416,"width":416,"date_captured":"2023-02-05T04:51:39+00:00"},{"id":46,"license":1,"file_name":"20211224_185936_jpg.rf.3eddefa9b80c35f725aed46533387fb6.jpg","height":416,"width":416,"date_captured":"2023-02-05T04:51:39+00:00"},{"id":47,"license":1,"file_name":"20211224_180851_jpg.rf.3eda8984d8bccdd8449c86a054904b5f.jpg","height":416,"width":416,"date_captured":"2023-02-05T04:51:39+00:00"},{"id":48,"license":1,"file_name":"20211224_190036_jpg.rf.437d5c1ecc5c34f5fd5beed8e42fc5d1.jpg","height":416,"width":416,"date_captured":"2023-02-05T04:51:39+00:00"},{"id":49,"license":1,"file_name":"20211224_181031_jpg.rf.44f96aa19093f0a21f5960e5c19e5424.jpg","height":416,"width":416,"date_captured":"2023-02-05T04:51:39+00:00"},{"id":50,"license":1,"file_name":"20211224_180306_jpg.rf.4437cd6113fc46ae80c2c1b5e97d162b.jpg","height":416,"width":416,"date_captured":"2023-02-05T04:51:39+00:00"},{"id":51,"license":1,"file_name":"20211224_180431_jpg.rf.45cbb913f923bc4b0378fc3d5b3a646e.jpg","height":416,"width":416,"date_captured":"2023-02-05T04:51:39+00:00"},{"id":52,"license":1,"file_name":"20211224_185507_jpg.rf.496b0685ab975bbc426d761d816ee327.jpg","height":416,"width":416,"date_captured":"2023-02-05T04:51:39+00:00"},{"id":53,"license":1,"file_name":"20211224_181034_jpg.rf.4b7da81c944a1402b8a441dc9a569b2e.jpg","height":416,"width":416,"date_captured":"2023-02-05T04:51:39+00:00"},{"id":54,"license":1,"file_name":"20211224_185957_jpg.rf.4b20f6ddf1b842c63f3c9912aee14391.jpg","height":416,"width":416,"date_captured":"2023-02-05T04:51:39+00:00"},{"id":55,"license":1,"file_name":"20211224_181120_jpg.rf.4ba54248a380eeee8ef2c084eaf1a520.jpg","height":416,"width":416,"date_captured":"2023-02-05T04:51:39+00:00"},{"id":56,"license":1,"file_name":"20211226_130648_jpg.rf.4bada82ddd2b7141cf34a55f3f37476b.jpg","height":416,"width":416,"date_captured":"2023-02-05T04:51:39+00:00"},{"id":57,"license":1,"file_name":"20211224_185413_jpg.rf.4c17bab17598ef69d2873632d806d5c7.jpg","height":416,"width":416,"date_captured":"2023-02-05T04:51:39+00:00"},{"id":58,"license":1,"file_name":"20211226_130659_jpg.rf.4d4a321e5cf2aff193c0c2a560fd4ae2.jpg","height":416,"width":416,"date_captured":"2023-02-05T04:51:39+00:00"},{"id":59,"license":1,"file_name":"20211224_181114_jpg.rf.4d6b5fcda5a0f039e58df7975a43de68.jpg","height":416,"width":416,"date_captured":"2023-02-05T04:51:39+00:00"},{"id":60,"license":1,"file_name":"20211224_180316_jpg.rf.50641b654d16a12192d470cd70258b41.jpg","height":416,"width":416,"date_captured":"2023-02-05T04:51:39+00:00"},{"id":61,"license":1,"file_name":"20211224_181051_jpg.rf.5362cc51250c5762609b398e0177757d.jpg","height":416,"width":416,"date_captured":"2023-02-05T04:51:39+00:00"},{"id":62,"license":1,"file_name":"20211224_180914_jpg.rf.550123a5d72fd55a7dbbccd3a73c7e76.jpg","height":416,"width":416,"date_captured":"2023-02-05T04:51:39+00:00"},{"id":63,"license":1,"file_name":"20211224_180726_jpg.rf.57cc646bb5969b0fcae14b17047933f9.jpg","height":416,"width":416,"date_captured":"2023-02-05T04:51:39+00:00"},{"id":64,"license":1,"file_name":"20211224_180717_jpg.rf.5859f3cb0bf05d31612401616473dfce.jpg","height":416,"width":416,"date_captured":"2023-02-05T04:51:39+00:00"},{"id":65,"license":1,"file_name":"20211224_180900_jpg.rf.58e85c20702f70f443375a0a78fb1553.jpg","height":416,"width":416,"date_captured":"2023-02-05T04:51:39+00:00"},{"id":66,"license":1,"file_name":"20211226_131212_jpg.rf.58ef07a4babef27284f756560485d43b.jpg","height":416,"width":416,"date_captured":"2023-02-05T04:51:39+00:00"},{"id":67,"license":1,"file_name":"20211224_190105_jpg.rf.5a61e6145e8ed0ce0ed8bf26f31f288a.jpg","height":416,"width":416,"date_captured":"2023-02-05T04:51:39+00:00"},{"id":68,"license":1,"file_name":"20211226_131220_jpg.rf.5ae50bdfc062192061d09bc7860b74ae.jpg","height":416,"width":416,"date_captured":"2023-02-05T04:51:39+00:00"},{"id":69,"license":1,"file_name":"20211226_130613_jpg.rf.5bb196cdf289cdc71ad40046b65094c9.jpg","height":416,"width":416,"date_captured":"2023-02-05T04:51:39+00:00"},{"id":70,"license":1,"file_name":"20211224_185516_jpg.rf.5c1321f393f25b92311575507f056910.jpg","height":416,"width":416,"date_captured":"2023-02-05T04:51:39+00:00"},{"id":71,"license":1,"file_name":"20211224_180337_jpg.rf.5e3fd0f6bdaee1adc83edf4db7bfe6c1.jpg","height":416,"width":416,"date_captured":"2023-02-05T04:51:39+00:00"},{"id":72,"license":1,"file_name":"20211224_181028_jpg.rf.5f752ff496aa092f3ee05d8a323845d3.jpg","height":416,"width":416,"date_captured":"2023-02-05T04:51:39+00:00"},{"id":73,"license":1,"file_name":"20211224_180333_jpg.rf.5c612a7b6295ceffaa8d59a046d835ae.jpg","height":416,"width":416,"date_captured":"2023-02-05T04:51:39+00:00"},{"id":74,"license":1,"file_name":"20211224_185445_jpg.rf.62968f72cfeea68fbf3fff31ca82c360.jpg","height":416,"width":416,"date_captured":"2023-02-05T04:51:39+00:00"},{"id":75,"license":1,"file_name":"20211224_185416_jpg.rf.61e84f6547812e8cce94344b527d9090.jpg","height":416,"width":416,"date_captured":"2023-02-05T04:51:39+00:00"},{"id":76,"license":1,"file_name":"20211224_185426_jpg.rf.646191c5973e27fa9b22614f2f52d617.jpg","height":416,"width":416,"date_captured":"2023-02-05T04:51:39+00:00"},{"id":77,"license":1,"file_name":"20211224_185953_jpg.rf.649bd343a898df1208b93d764064fd68.jpg","height":416,"width":416,"date_captured":"2023-02-05T04:51:39+00:00"},{"id":78,"license":1,"file_name":"20211224_180840_jpg.rf.689f358849cb2e498a51703d8e25b33b.jpg","height":416,"width":416,"date_captured":"2023-02-05T04:51:39+00:00"},{"id":79,"license":1,"file_name":"20211226_130615_jpg.rf.67c917e47d68bc8008a6380322a9397c.jpg","height":416,"width":416,"date_captured":"2023-02-05T04:51:39+00:00"},{"id":80,"license":1,"file_name":"20211224_180747_jpg.rf.674a92926ff63fdc415178c06ff316ad.jpg","height":416,"width":416,"date_captured":"2023-02-05T04:51:39+00:00"},{"id":81,"license":1,"file_name":"20211226_130700_jpg.rf.698601de90b2b07e02eefb9f78c1acda.jpg","height":416,"width":416,"date_captured":"2023-02-05T04:51:39+00:00"},{"id":82,"license":1,"file_name":"20211226_131214_jpg.rf.6d062d94b560cd6b6cdf48a2bf4b8947.jpg","height":416,"width":416,"date_captured":"2023-02-05T04:51:39+00:00"},{"id":83,"license":1,"file_name":"20211224_180834_jpg.rf.6cd09e3a6d17f3a11236bc546636ce71.jpg","height":416,"width":416,"date_captured":"2023-02-05T04:51:39+00:00"},{"id":84,"license":1,"file_name":"20211224_180819_jpg.rf.6cde6a852c7159fe8f5dfd8ff361812a.jpg","height":416,"width":416,"date_captured":"2023-02-05T04:51:39+00:00"},{"id":85,"license":1,"file_name":"20211226_130624_jpg.rf.6dedc2ee57ef3e072af2176db3e46665.jpg","height":416,"width":416,"date_captured":"2023-02-05T04:51:39+00:00"},{"id":86,"license":1,"file_name":"20211224_185514_jpg.rf.6e33ff25464e3cd03cc6399ea326422e.jpg","height":416,"width":416,"date_captured":"2023-02-05T04:51:39+00:00"},{"id":87,"license":1,"file_name":"20211226_131238_jpg.rf.7324898036ba58bf2b97386472a7cfee.jpg","height":416,"width":416,"date_captured":"2023-02-05T04:51:39+00:00"},{"id":88,"license":1,"file_name":"20211226_130646_jpg.rf.6f4456fda9665facb7ea233e6c289d91.jpg","height":416,"width":416,"date_captured":"2023-02-05T04:51:39+00:00"},{"id":89,"license":1,"file_name":"20211224_181102_jpg.rf.7346b8559d8d9f6d317acf14629fed89.jpg","height":416,"width":416,"date_captured":"2023-02-05T04:51:39+00:00"},{"id":90,"license":1,"file_name":"20211226_131213_jpg.rf.765de983ace3dbf1258526469d589ee4.jpg","height":416,"width":416,"date_captured":"2023-02-05T04:51:39+00:00"},{"id":91,"license":1,"file_name":"20211226_131246_jpg.rf.772566188bd992b82cf7604365a4e7e5.jpg","height":416,"width":416,"date_captured":"2023-02-05T04:51:39+00:00"},{"id":92,"license":1,"file_name":"20211224_185945_jpg.rf.7970eeabdda4a13f72ad33440c3044e8.jpg","height":416,"width":416,"date_captured":"2023-02-05T04:51:39+00:00"},{"id":93,"license":1,"file_name":"20211226_130657_jpg.rf.76bd0972819bca3ddd301e3f50ae2dc9.jpg","height":416,"width":416,"date_captured":"2023-02-05T04:51:39+00:00"},{"id":94,"license":1,"file_name":"20211226_131306_jpg.rf.80d4dc00e24352072ce88ab339490c1f.jpg","height":416,"width":416,"date_captured":"2023-02-05T04:51:39+00:00"},{"id":95,"license":1,"file_name":"20211224_181036_jpg.rf.7cc80377e57a2fcc627141179afaaf32.jpg","height":416,"width":416,"date_captured":"2023-02-05T04:51:39+00:00"},{"id":96,"license":1,"file_name":"20211226_131308_jpg.rf.81c7611b6f71673c55420e7410807785.jpg","height":416,"width":416,"date_captured":"2023-02-05T04:51:39+00:00"},{"id":97,"license":1,"file_name":"20211224_185453_jpg.rf.84cbbf29ff9dd25fb1c778cd0fb9f44b.jpg","height":416,"width":416,"date_captured":"2023-02-05T04:51:39+00:00"},{"id":98,"license":1,"file_name":"20211224_190000_jpg.rf.85b92eeb2603bb738fbf8526f3116624.jpg","height":416,"width":416,"date_captured":"2023-02-05T04:51:39+00:00"},{"id":99,"license":1,"file_name":"20211224_180458_jpg.rf.8675ac80f627148e2b78bfdf0cd43a0a.jpg","height":416,"width":416,"date_captured":"2023-02-05T04:51:39+00:00"},{"id":100,"license":1,"file_name":"20211224_185940_jpg.rf.87aa2267144a8013c41d4e84c1c61aae.jpg","height":416,"width":416,"date_captured":"2023-02-05T04:51:39+00:00"},{"id":101,"license":1,"file_name":"20211224_185512_jpg.rf.86bd7d07a8b52a31a69385d659a7c2c7.jpg","height":416,"width":416,"date_captured":"2023-02-05T04:51:39+00:00"},{"id":102,"license":1,"file_name":"20211224_180347_jpg.rf.8a45f9650a1f04ea8b08cf1f23ef419e.jpg","height":416,"width":416,"date_captured":"2023-02-05T04:51:39+00:00"},{"id":103,"license":1,"file_name":"20211226_131231_jpg.rf.8aa9a1ce79d6cc440073428e010843c6.jpg","height":416,"width":416,"date_captured":"2023-02-05T04:51:39+00:00"},{"id":104,"license":1,"file_name":"20211224_185434_jpg.rf.8d1a57f910eeebb9ea97228b1ea75201.jpg","height":416,"width":416,"date_captured":"2023-02-05T04:51:39+00:00"},{"id":105,"license":1,"file_name":"20211224_185421_jpg.rf.8c46b841a8d22ae6a32cf7d1674b651e.jpg","height":416,"width":416,"date_captured":"2023-02-05T04:51:39+00:00"},{"id":106,"license":1,"file_name":"20211224_180425_jpg.rf.8e1fcedf01c1f3c0304be909fc83abf8.jpg","height":416,"width":416,"date_captured":"2023-02-05T04:51:39+00:00"},{"id":107,"license":1,"file_name":"20211224_181111_jpg.rf.8fa7b457d96990e5bf8d52904c0a09ec.jpg","height":416,"width":416,"date_captured":"2023-02-05T04:51:39+00:00"},{"id":108,"license":1,"file_name":"20211226_130644_jpg.rf.8fcc617dab141efdecbfebe595890fef.jpg","height":416,"width":416,"date_captured":"2023-02-05T04:51:39+00:00"},{"id":109,"license":1,"file_name":"20211224_190058_jpg.rf.90591f33d888404ffcab26b8d51b5544.jpg","height":416,"width":416,"date_captured":"2023-02-05T04:51:39+00:00"},{"id":110,"license":1,"file_name":"20211226_130644-0-_jpg.rf.91e4b66e1156492f7336fc9b9d227f9b.jpg","height":416,"width":416,"date_captured":"2023-02-05T04:51:39+00:00"},{"id":111,"license":1,"file_name":"20211224_185410_jpg.rf.92800cc97901477c7ad8906bc6c90f7e.jpg","height":416,"width":416,"date_captured":"2023-02-05T04:51:39+00:00"},{"id":112,"license":1,"file_name":"20211224_185948_jpg.rf.92811e24a413700f9fa67df5f2af8130.jpg","height":416,"width":416,"date_captured":"2023-02-05T04:51:39+00:00"},{"id":113,"license":1,"file_name":"20211224_185408_jpg.rf.93e0f66e10202ef6ad93ccadc96efd60.jpg","height":416,"width":416,"date_captured":"2023-02-05T04:51:39+00:00"},{"id":114,"license":1,"file_name":"20211226_130630_jpg.rf.94cbb519b5998b2343e56408786ff6f0.jpg","height":416,"width":416,"date_captured":"2023-02-05T04:51:39+00:00"},{"id":115,"license":1,"file_name":"20211224_180310_jpg.rf.9644378fbeedde653f7814b5cb762022.jpg","height":416,"width":416,"date_captured":"2023-02-05T04:51:39+00:00"},{"id":116,"license":1,"file_name":"20211224_180513_jpg.rf.962acaa888755bd6ed6faea2ff3dfd16.jpg","height":416,"width":416,"date_captured":"2023-02-05T04:51:39+00:00"},{"id":117,"license":1,"file_name":"20211224_185938_jpg.rf.985a4d5960ae71c12ce1cda40e8afc8b.jpg","height":416,"width":416,"date_captured":"2023-02-05T04:51:39+00:00"},{"id":118,"license":1,"file_name":"20211224_180752_jpg.rf.9958bfea0d55127e6c2a34cbdbd55c76.jpg","height":416,"width":416,"date_captured":"2023-02-05T04:51:39+00:00"},{"id":119,"license":1,"file_name":"20211226_130629_jpg.rf.998d096790be19a423e104dbb0fc0228.jpg","height":416,"width":416,"date_captured":"2023-02-05T04:51:39+00:00"},{"id":120,"license":1,"file_name":"20211226_130635_jpg.rf.9ac2068d41283d19decce82692b6ae0d.jpg","height":416,"width":416,"date_captured":"2023-02-05T04:51:39+00:00"},{"id":121,"license":1,"file_name":"20211224_181116_jpg.rf.9ba6e177d371a222377ff5e22070a5b9.jpg","height":416,"width":416,"date_captured":"2023-02-05T04:51:39+00:00"},{"id":122,"license":1,"file_name":"20211224_180856_jpg.rf.9d5f26398a4b8d91333cad105359645c.jpg","height":416,"width":416,"date_captured":"2023-02-05T04:51:39+00:00"},{"id":123,"license":1,"file_name":"20211226_131243_jpg.rf.a04baa1854d94d20842c5f007b77c9c5.jpg","height":416,"width":416,"date_captured":"2023-02-05T04:51:39+00:00"},{"id":124,"license":1,"file_name":"20211224_180356_jpg.rf.a442b89e912178c28bfb9b826aca8eef.jpg","height":416,"width":416,"date_captured":"2023-02-05T04:51:39+00:00"},{"id":125,"license":1,"file_name":"20211224_180729_jpg.rf.a52af227f723bb68e473ee814f838c5c.jpg","height":416,"width":416,"date_captured":"2023-02-05T04:51:39+00:00"},{"id":126,"license":1,"file_name":"20211226_131217_jpg.rf.a52bda502e73378f327f93f974d3d092.jpg","height":416,"width":416,"date_captured":"2023-02-05T04:51:39+00:00"},{"id":127,"license":1,"file_name":"20211224_185501_jpg.rf.a75fff0fa8954501261b32521ab57184.jpg","height":416,"width":416,"date_captured":"2023-02-05T04:51:39+00:00"},{"id":128,"license":1,"file_name":"20211226_130618_jpg.rf.a9157546ef2f36b6476edebc064bb776.jpg","height":416,"width":416,"date_captured":"2023-02-05T04:51:39+00:00"},{"id":129,"license":1,"file_name":"20211224_185930_jpg.rf.ab149372d86c9d2c141855f64ef646fd.jpg","height":416,"width":416,"date_captured":"2023-02-05T04:51:39+00:00"},{"id":130,"license":1,"file_name":"20211224_181119_jpg.rf.ab475f9a767844d1d36126a26270cf49.jpg","height":416,"width":416,"date_captured":"2023-02-05T04:51:39+00:00"},{"id":131,"license":1,"file_name":"20211226_130652_jpg.rf.ad75455ec84788f4fbdbd1237b3c518b.jpg","height":416,"width":416,"date_captured":"2023-02-05T04:51:39+00:00"},{"id":132,"license":1,"file_name":"20211226_131304_jpg.rf.abacf9d2e821a466949388995d6fb56d.jpg","height":416,"width":416,"date_captured":"2023-02-05T04:51:39+00:00"},{"id":133,"license":1,"file_name":"20211224_180854_jpg.rf.ad9e3160271e2077ae103ba4dbddf63f.jpg","height":416,"width":416,"date_captured":"2023-02-05T04:51:39+00:00"},{"id":134,"license":1,"file_name":"20211224_185955_jpg.rf.af179b4152afb1aff7c367e672b6d50e.jpg","height":416,"width":416,"date_captured":"2023-02-05T04:51:39+00:00"},{"id":135,"license":1,"file_name":"20211226_131247_jpg.rf.b1400c7e88cd8c66a1ff750f6df74be1.jpg","height":416,"width":416,"date_captured":"2023-02-05T04:51:39+00:00"},{"id":136,"license":1,"file_name":"20211224_181121_jpg.rf.b4cf0fd69eb14d78d7bf7c526f37e2b0.jpg","height":416,"width":416,"date_captured":"2023-02-05T04:51:39+00:00"},{"id":137,"license":1,"file_name":"20211224_180434_jpg.rf.b538279eb7f6ea0e407710ba35e7abed.jpg","height":416,"width":416,"date_captured":"2023-02-05T04:51:39+00:00"},{"id":138,"license":1,"file_name":"20211224_181123_jpg.rf.b6cb8b34407187e580c0b68ea7d677da.jpg","height":416,"width":416,"date_captured":"2023-02-05T04:51:39+00:00"},{"id":139,"license":1,"file_name":"20211226_130621_jpg.rf.b87a79e07303b788a8070a8b2a95501f.jpg","height":416,"width":416,"date_captured":"2023-02-05T04:51:39+00:00"},{"id":140,"license":1,"file_name":"20211224_190107_jpg.rf.b8cfa4c8cffb408676dbe74815264062.jpg","height":416,"width":416,"date_captured":"2023-02-05T04:51:39+00:00"},{"id":141,"license":1,"file_name":"20211224_180414_jpg.rf.ba9326a6fd3897c8842b6a404673cdf8.jpg","height":416,"width":416,"date_captured":"2023-02-05T04:51:39+00:00"},{"id":142,"license":1,"file_name":"20211224_185441_jpg.rf.ba538e0d8d70becc593379c021aa58d1.jpg","height":416,"width":416,"date_captured":"2023-02-05T04:51:39+00:00"},{"id":143,"license":1,"file_name":"20211224_180842_jpg.rf.bb186195fc52ef6b053df6b7731c4661.jpg","height":416,"width":416,"date_captured":"2023-02-05T04:51:39+00:00"},{"id":144,"license":1,"file_name":"20211226_130638_jpg.rf.bba8c42fa1a8735a6404f39855542270.jpg","height":416,"width":416,"date_captured":"2023-02-05T04:51:39+00:00"},{"id":145,"license":1,"file_name":"20211226_131245_jpg.rf.bd85be5018fe63ec6ffc6b48aae99ce1.jpg","height":416,"width":416,"date_captured":"2023-02-05T04:51:39+00:00"},{"id":146,"license":1,"file_name":"20211226_131314_jpg.rf.be49b0d3ae6e9a3b3e53ede5e38abed0.jpg","height":416,"width":416,"date_captured":"2023-02-05T04:51:39+00:00"},{"id":147,"license":1,"file_name":"20211224_190035_jpg.rf.be73cf40f661a7b75d124d2db6ea4ca9.jpg","height":416,"width":416,"date_captured":"2023-02-05T04:51:39+00:00"},{"id":148,"license":1,"file_name":"20211224_180504_jpg.rf.be7b089e9b45445979ba1d0da7cd08db.jpg","height":416,"width":416,"date_captured":"2023-02-05T04:51:39+00:00"},{"id":149,"license":1,"file_name":"20211226_130650_jpg.rf.be77cf96b2454866303f263de8f1d12b.jpg","height":416,"width":416,"date_captured":"2023-02-05T04:51:39+00:00"},{"id":150,"license":1,"file_name":"20211224_190029_jpg.rf.bee23883c83b024deec1e8585855ccc7.jpg","height":416,"width":416,"date_captured":"2023-02-05T04:51:39+00:00"},{"id":151,"license":1,"file_name":"20211226_131249_jpg.rf.bf8528aac527e03ec17998b8d2befd9c.jpg","height":416,"width":416,"date_captured":"2023-02-05T04:51:39+00:00"},{"id":152,"license":1,"file_name":"20211224_180713_jpg.rf.c1f46ee8da9a4060e923111c727d14ec.jpg","height":416,"width":416,"date_captured":"2023-02-05T04:51:39+00:00"},{"id":153,"license":1,"file_name":"20211224_190032_jpg.rf.c36f86acf2846b9df4931d31760f49ee.jpg","height":416,"width":416,"date_captured":"2023-02-05T04:51:39+00:00"},{"id":154,"license":1,"file_name":"20211224_190024_jpg.rf.c08d62916ffa6733faa4e88f9c9861be.jpg","height":416,"width":416,"date_captured":"2023-02-05T04:51:39+00:00"},{"id":155,"license":1,"file_name":"20211224_185952_jpg.rf.c7bda64f65493a5e9be4b85455a6b2d1.jpg","height":416,"width":416,"date_captured":"2023-02-05T04:51:39+00:00"},{"id":156,"license":1,"file_name":"20211226_130641_jpg.rf.c5b050db22841624fc73c394f3196c6f.jpg","height":416,"width":416,"date_captured":"2023-02-05T04:51:39+00:00"},{"id":157,"license":1,"file_name":"20211224_185446_jpg.rf.c85c6a44705b90381fca1fe934ba3248.jpg","height":416,"width":416,"date_captured":"2023-02-05T04:51:39+00:00"},{"id":158,"license":1,"file_name":"20211226_131241_jpg.rf.c9f644f77eb460425a7909de0ae266d4.jpg","height":416,"width":416,"date_captured":"2023-02-05T04:51:39+00:00"},{"id":159,"license":1,"file_name":"20211226_131233_jpg.rf.ca44699658afde7a0c3e64f507043479.jpg","height":416,"width":416,"date_captured":"2023-02-05T04:51:39+00:00"},{"id":160,"license":1,"file_name":"20211224_185502_jpg.rf.cbf17d23037269c1fbf1c90fa5c23df5.jpg","height":416,"width":416,"date_captured":"2023-02-05T04:51:39+00:00"},{"id":161,"license":1,"file_name":"20211224_181045_jpg.rf.cc0d55ed387a06a472e050892db0ab03.jpg","height":416,"width":416,"date_captured":"2023-02-05T04:51:39+00:00"},{"id":162,"license":1,"file_name":"20211224_190012_jpg.rf.cd9f1ec93c9f1cf2ee7a2b00e98ece68.jpg","height":416,"width":416,"date_captured":"2023-02-05T04:51:39+00:00"},{"id":163,"license":1,"file_name":"20211224_185947_jpg.rf.d0130bf0d98d5035ce58b652626f7f9c.jpg","height":416,"width":416,"date_captured":"2023-02-05T04:51:39+00:00"},{"id":164,"license":1,"file_name":"20211224_180446_jpg.rf.cfcf048b0f09502ad8f3dabab873bce1.jpg","height":416,"width":416,"date_captured":"2023-02-05T04:51:39+00:00"},{"id":165,"license":1,"file_name":"20211226_131240_jpg.rf.d1186aa4b3dafa190d4b9a8a702a99e9.jpg","height":416,"width":416,"date_captured":"2023-02-05T04:51:39+00:00"},{"id":166,"license":1,"file_name":"20211224_185523_jpg.rf.d11b737d2a1ff48d91d822a9301fe234.jpg","height":416,"width":416,"date_captured":"2023-02-05T04:51:39+00:00"},{"id":167,"license":1,"file_name":"20211224_181057_jpg.rf.d16213e36e9a81af9e3be63400ff5f4e.jpg","height":416,"width":416,"date_captured":"2023-02-05T04:51:39+00:00"},{"id":168,"license":1,"file_name":"20211224_185526_jpg.rf.d195871ebdee31310504a1d52b0e1809.jpg","height":416,"width":416,"date_captured":"2023-02-05T04:51:39+00:00"},{"id":169,"license":1,"file_name":"20211224_185451_jpg.rf.d22b8bc6f610225e2c56480c6106c7bc.jpg","height":416,"width":416,"date_captured":"2023-02-05T04:51:39+00:00"},{"id":170,"license":1,"file_name":"20211224_180517_jpg.rf.d370de3ac4073d36df6f54292efc292c.jpg","height":416,"width":416,"date_captured":"2023-02-05T04:51:39+00:00"},{"id":171,"license":1,"file_name":"20211226_131257_jpg.rf.d3460d6a7827c1b73890c654ce9fc99e.jpg","height":416,"width":416,"date_captured":"2023-02-05T04:51:39+00:00"},{"id":172,"license":1,"file_name":"20211226_130640_jpg.rf.d3e5b282485993607e7c0da860f9f432.jpg","height":416,"width":416,"date_captured":"2023-02-05T04:51:39+00:00"},{"id":173,"license":1,"file_name":"20211224_185459_jpg.rf.d410ea5e4854b867704f3f557f687ce1.jpg","height":416,"width":416,"date_captured":"2023-02-05T04:51:39+00:00"},{"id":174,"license":1,"file_name":"20211224_181124_jpg.rf.d54c82b0a94de0d1d71abac391a4e0d7.jpg","height":416,"width":416,"date_captured":"2023-02-05T04:51:39+00:00"},{"id":175,"license":1,"file_name":"20211224_190050_jpg.rf.d697020c8b645717e018c503a70eb720.jpg","height":416,"width":416,"date_captured":"2023-02-05T04:51:39+00:00"},{"id":176,"license":1,"file_name":"20211226_130702_jpg.rf.da77ac694554ef801558238ea8df9436.jpg","height":416,"width":416,"date_captured":"2023-02-05T04:51:39+00:00"},{"id":177,"license":1,"file_name":"20211226_130619_jpg.rf.dbb4b08c5d7474df99ca5c7b6ddf8b6d.jpg","height":416,"width":416,"date_captured":"2023-02-05T04:51:39+00:00"},{"id":178,"license":1,"file_name":"20211224_180448_jpg.rf.dc88a90988d44fbc2a2796a50b584a00.jpg","height":416,"width":416,"date_captured":"2023-02-05T04:51:39+00:00"},{"id":179,"license":1,"file_name":"20211224_185506_jpg.rf.de282f1031986196f66b8a3ea2d79f9a.jpg","height":416,"width":416,"date_captured":"2023-02-05T04:51:39+00:00"},{"id":180,"license":1,"file_name":"20211224_180827_jpg.rf.df8eb99623b81e4e01f824be54da3364.jpg","height":416,"width":416,"date_captured":"2023-02-05T04:51:39+00:00"},{"id":181,"license":1,"file_name":"20211224_180510_jpg.rf.e3abd475d805abf8be6e2675920355ee.jpg","height":416,"width":416,"date_captured":"2023-02-05T04:51:39+00:00"},{"id":182,"license":1,"file_name":"20211224_185430_jpg.rf.e40a424e417d018e8406a904b66393bb.jpg","height":416,"width":416,"date_captured":"2023-02-05T04:51:39+00:00"},{"id":183,"license":1,"file_name":"20211224_185525_jpg.rf.e66698fb11416c4a948dc27fefc24409.jpg","height":416,"width":416,"date_captured":"2023-02-05T04:51:39+00:00"},{"id":184,"license":1,"file_name":"20211224_180813_jpg.rf.e8f2ef2cf741e1499fb0cf73342f9bd3.jpg","height":416,"width":416,"date_captured":"2023-02-05T04:51:39+00:00"},{"id":185,"license":1,"file_name":"20211226_131234_jpg.rf.ea7bc3f9275a22df078630beb79ba579.jpg","height":416,"width":416,"date_captured":"2023-02-05T04:51:39+00:00"},{"id":186,"license":1,"file_name":"20211224_190055_jpg.rf.ea969f72969418859c7da50de3d4a33d.jpg","height":416,"width":416,"date_captured":"2023-02-05T04:51:39+00:00"},{"id":187,"license":1,"file_name":"20211226_131221_jpg.rf.ead8c00fec631cec95c2d814c1c1d814.jpg","height":416,"width":416,"date_captured":"2023-02-05T04:51:39+00:00"},{"id":188,"license":1,"file_name":"20211226_131309_jpg.rf.eb4ba919a94f658ca0329d46b242c270.jpg","height":416,"width":416,"date_captured":"2023-02-05T04:51:39+00:00"},{"id":189,"license":1,"file_name":"20211224_185414_jpg.rf.ec1a65b68cadb2fa888fd03c5c456f25.jpg","height":416,"width":416,"date_captured":"2023-02-05T04:51:39+00:00"},{"id":190,"license":1,"file_name":"20211224_180824_jpg.rf.ed53e7247ffd419429e1b20b1b573442.jpg","height":416,"width":416,"date_captured":"2023-02-05T04:51:39+00:00"},{"id":191,"license":1,"file_name":"20211224_180344_jpg.rf.ee15c3b0f84af497e9891cf5331fca42.jpg","height":416,"width":416,"date_captured":"2023-02-05T04:51:39+00:00"},{"id":192,"license":1,"file_name":"20211224_185527_jpg.rf.f0dadfc7c389417f5885b4552ff5df4e.jpg","height":416,"width":416,"date_captured":"2023-02-05T04:51:39+00:00"},{"id":193,"license":1,"file_name":"20211224_180417_jpg.rf.f131dec709583fed4b93e6a93ce30876.jpg","height":416,"width":416,"date_captured":"2023-02-05T04:51:39+00:00"},{"id":194,"license":1,"file_name":"20211224_181108_jpg.rf.f15c83d994a1828aec71c00c436d9d8e.jpg","height":416,"width":416,"date_captured":"2023-02-05T04:51:39+00:00"},{"id":195,"license":1,"file_name":"20211224_180422_jpg.rf.f544e68d9f0ab9e0da05ffa57ad17c99.jpg","height":416,"width":416,"date_captured":"2023-02-05T04:51:39+00:00"},{"id":196,"license":1,"file_name":"20211226_131230_jpg.rf.f7896f7c97b5e7f69e640985e3d5c637.jpg","height":416,"width":416,"date_captured":"2023-02-05T04:51:39+00:00"},{"id":197,"license":1,"file_name":"20211224_181037_jpg.rf.f85ad736c0845590902a3b09437396e5.jpg","height":416,"width":416,"date_captured":"2023-02-05T04:51:39+00:00"},{"id":198,"license":1,"file_name":"20211226_131218_jpg.rf.f899f6d49be4962d7952785dcf256f14.jpg","height":416,"width":416,"date_captured":"2023-02-05T04:51:39+00:00"},{"id":199,"license":1,"file_name":"20211224_185931_jpg.rf.f8e97f8993867d1649498813428497b1.jpg","height":416,"width":416,"date_captured":"2023-02-05T04:51:39+00:00"},{"id":200,"license":1,"file_name":"20211224_181100_jpg.rf.fc378a821722bca8adc165225fbc436f.jpg","height":416,"width":416,"date_captured":"2023-02-05T04:51:39+00:00"},{"id":201,"license":1,"file_name":"20211224_180330_jpg.rf.fd42680c85c3a389b33e71b14e5a2607.jpg","height":416,"width":416,"date_captured":"2023-02-05T04:51:39+00:00"},{"id":202,"license":1,"file_name":"20211224_181030_jpg.rf.fe219d21724fa4e2edc6d028fc041bb7.jpg","height":416,"width":416,"date_captured":"2023-02-05T04:51:39+00:00"},{"id":203,"license":1,"file_name":"20211226_131228_jpg.rf.fed805145bba8b8685e397cb53d32ffd.jpg","height":416,"width":416,"date_captured":"2023-02-05T04:51:39+00:00"},{"id":204,"license":1,"file_name":"20211224_190053_jpg.rf.fee9ebaf6adc507639431594c636251a.jpg","height":416,"width":416,"date_captured":"2023-02-05T04:51:39+00:00"},{"id":205,"license":1,"file_name":"20211224_181041_jpg.rf.ffec30703ef339c757a26926c894f3a4.jpg","height":416,"width":416,"date_captured":"2023-02-05T04:51:39+00:00"}],"annotations":[{"id":0,"image_id":0,"category_id":2,"bbox":[109,164,209.5,157],"area":32891.5,"segmentation":[],"iscrowd":0},{"id":1,"image_id":1,"category_id":4,"bbox":[143,45,1.5,1],"area":1.5,"segmentation":[],"iscrowd":0},{"id":2,"image_id":1,"category_id":4,"bbox":[159,33,196,314],"area":61544,"segmentation":[],"iscrowd":0},{"id":3,"image_id":2,"category_id":2,"bbox":[77,122,232.5,176],"area":40920,"segmentation":[],"iscrowd":0},{"id":4,"image_id":3,"category_id":1,"bbox":[119,182,76.5,179],"area":13693.5,"segmentation":[],"iscrowd":0},{"id":5,"image_id":3,"category_id":1,"bbox":[222,88,57,123.5],"area":7039.5,"segmentation":[],"iscrowd":0},{"id":6,"image_id":3,"category_id":1,"bbox":[232,244,57,97.5],"area":5557.5,"segmentation":[],"iscrowd":0},{"id":7,"image_id":3,"category_id":1,"bbox":[169,205,67.5,22],"area":1485,"segmentation":[],"iscrowd":0},{"id":8,"image_id":3,"category_id":1,"bbox":[100,88,215.5,23],"area":4956.5,"segmentation":[],"iscrowd":0},{"id":9,"image_id":4,"category_id":3,"bbox":[201,101,129,144.5],"area":18640.5,"segmentation":[],"iscrowd":0},{"id":10,"image_id":5,"category_id":4,"bbox":[95,17,230.5,318.5],"area":73414.25,"segmentation":[],"iscrowd":0},{"id":11,"image_id":5,"category_id":4,"bbox":[259,136,87.5,91.5],"area":8006.25,"segmentation":[],"iscrowd":0},{"id":12,"image_id":5,"category_id":4,"bbox":[242,20,74.5,94],"area":7003,"segmentation":[],"iscrowd":0},{"id":13,"image_id":6,"category_id":4,"bbox":[143,84,147,142.5],"area":20947.5,"segmentation":[],"iscrowd":0},{"id":14,"image_id":6,"category_id":4,"bbox":[217,92,56.5,60.5],"area":3418.25,"segmentation":[],"iscrowd":0},{"id":15,"image_id":6,"category_id":4,"bbox":[239,53,20,45],"area":900,"segmentation":[],"iscrowd":0},{"id":16,"image_id":6,"category_id":4,"bbox":[304,51,38.5,95.5],"area":3676.75,"segmentation":[],"iscrowd":0},{"id":17,"image_id":6,"category_id":4,"bbox":[158,210,83,40],"area":3320,"segmentation":[],"iscrowd":0},{"id":18,"image_id":7,"category_id":4,"bbox":[78,92,295.5,161.5],"area":47723.25,"segmentation":[],"iscrowd":0},{"id":19,"image_id":7,"category_id":4,"bbox":[166,258,111.5,50],"area":5575,"segmentation":[],"iscrowd":0},{"id":20,"image_id":7,"category_id":4,"bbox":[260,60,17.5,75],"area":1312.5,"segmentation":[],"iscrowd":0},{"id":21,"image_id":7,"category_id":4,"bbox":[145,58,20,48],"area":960,"segmentation":[],"iscrowd":0},{"id":22,"image_id":8,"category_id":1,"bbox":[64,101,246,299.5],"area":73677,"segmentation":[],"iscrowd":0},{"id":23,"image_id":8,"category_id":1,"bbox":[227,318,38,78.5],"area":2983,"segmentation":[],"iscrowd":0},{"id":24,"image_id":9,"category_id":3,"bbox":[118,125,112.5,104],"area":11700,"segmentation":[],"iscrowd":0},{"id":25,"image_id":10,"category_id":3,"bbox":[168,100,147,151.5],"area":22270.5,"segmentation":[],"iscrowd":0},{"id":26,"image_id":11,"category_id":3,"bbox":[179,116,97.5,116],"area":11310,"segmentation":[],"iscrowd":0},{"id":27,"image_id":12,"category_id":2,"bbox":[92,82,223.5,169.5],"area":37883.25,"segmentation":[],"iscrowd":0},{"id":28,"image_id":13,"category_id":2,"bbox":[61,115,300,224],"area":67200,"segmentation":[],"iscrowd":0},{"id":29,"image_id":14,"category_id":4,"bbox":[89,53,263.5,230],"area":60605,"segmentation":[],"iscrowd":0},{"id":30,"image_id":14,"category_id":4,"bbox":[155,56,13,51],"area":663,"segmentation":[],"iscrowd":0},{"id":31,"image_id":15,"category_id":4,"bbox":[166,64,175,207.5],"area":36312.5,"segmentation":[],"iscrowd":0},{"id":32,"image_id":15,"category_id":4,"bbox":[298,44,20,50],"area":1000,"segmentation":[],"iscrowd":0},{"id":33,"image_id":15,"category_id":4,"bbox":[218,52,46.5,53],"area":2464.5,"segmentation":[],"iscrowd":0},{"id":34,"image_id":16,"category_id":1,"bbox":[92,95,246.5,302.5],"area":74566.25,"segmentation":[],"iscrowd":0},{"id":35,"image_id":16,"category_id":1,"bbox":[167,232,81.5,24.5],"area":1996.75,"segmentation":[],"iscrowd":0},{"id":36,"image_id":16,"category_id":1,"bbox":[213,296,82.5,98.5],"area":8126.25,"segmentation":[],"iscrowd":0},{"id":37,"image_id":17,"category_id":2,"bbox":[120,153,225,170.5],"area":38362.5,"segmentation":[],"iscrowd":0},{"id":38,"image_id":18,"category_id":1,"bbox":[111,12,221,345],"area":76245,"segmentation":[],"iscrowd":0},{"id":39,"image_id":18,"category_id":1,"bbox":[203,171,68.5,20],"area":1370,"segmentation":[],"iscrowd":0},{"id":40,"image_id":19,"category_id":4,"bbox":[93,67,249.5,162.5],"area":40543.75,"segmentation":[],"iscrowd":0},{"id":41,"image_id":19,"category_id":4,"bbox":[153,66,12.5,35.5],"area":443.75,"segmentation":[],"iscrowd":0},{"id":42,"image_id":19,"category_id":4,"bbox":[170,240,96,42.5],"area":4080,"segmentation":[],"iscrowd":0},{"id":43,"image_id":20,"category_id":2,"bbox":[110,108,243.5,184],"area":44804,"segmentation":[],"iscrowd":0},{"id":44,"image_id":21,"category_id":4,"bbox":[204,107,182.5,115.5],"area":21078.75,"segmentation":[],"iscrowd":0},{"id":45,"image_id":21,"category_id":4,"bbox":[348,98,10,32],"area":320,"segmentation":[],"iscrowd":0},{"id":46,"image_id":21,"category_id":4,"bbox":[269,100,10,46.5],"area":465,"segmentation":[],"iscrowd":0},{"id":47,"image_id":21,"category_id":4,"bbox":[253,229,74.5,25.5],"area":1899.75,"segmentation":[],"iscrowd":0},{"id":48,"image_id":22,"category_id":2,"bbox":[154,143,200.5,150],"area":30075,"segmentation":[],"iscrowd":0},{"id":49,"image_id":23,"category_id":1,"bbox":[40,20,243.5,316.5],"area":77067.75,"segmentation":[],"iscrowd":0},{"id":50,"image_id":23,"category_id":1,"bbox":[135,159,78.5,19.5],"area":1530.75,"segmentation":[],"iscrowd":0},{"id":51,"image_id":24,"category_id":1,"bbox":[40,27,255,322.5],"area":82237.5,"segmentation":[],"iscrowd":0},{"id":52,"image_id":24,"category_id":1,"bbox":[198,256,90.5,89],"area":8054.5,"segmentation":[],"iscrowd":0},{"id":53,"image_id":25,"category_id":4,"bbox":[92,71,223.5,179.5],"area":40118.25,"segmentation":[],"iscrowd":0},{"id":54,"image_id":25,"category_id":4,"bbox":[301,71,17,60.5],"area":1028.5,"segmentation":[],"iscrowd":0},{"id":55,"image_id":25,"category_id":4,"bbox":[297,131,47.5,42.5],"area":2018.75,"segmentation":[],"iscrowd":0},{"id":56,"image_id":25,"category_id":4,"bbox":[173,254,94,51],"area":4794,"segmentation":[],"iscrowd":0},{"id":57,"image_id":26,"category_id":1,"bbox":[27,19,251,174],"area":43674,"segmentation":[],"iscrowd":0},{"id":58,"image_id":26,"category_id":1,"bbox":[126,178,99,16],"area":1584,"segmentation":[],"iscrowd":0},{"id":59,"image_id":26,"category_id":1,"bbox":[97,262,188,119],"area":22372,"segmentation":[],"iscrowd":0},{"id":60,"image_id":27,"category_id":3,"bbox":[140,127,143,168],"area":24024,"segmentation":[],"iscrowd":0},{"id":61,"image_id":28,"category_id":1,"bbox":[82,67,164.5,297],"area":48856.5,"segmentation":[],"iscrowd":0},{"id":62,"image_id":28,"category_id":1,"bbox":[217,258,67.5,84],"area":5670,"segmentation":[],"iscrowd":0},{"id":63,"image_id":28,"category_id":1,"bbox":[254,74,32,16.5],"area":528,"segmentation":[],"iscrowd":0},{"id":64,"image_id":28,"category_id":1,"bbox":[165,195,73.5,19.5],"area":1433.25,"segmentation":[],"iscrowd":0},{"id":65,"image_id":29,"category_id":4,"bbox":[119,1,216.5,312.5],"area":67656.25,"segmentation":[],"iscrowd":0},{"id":66,"image_id":29,"category_id":4,"bbox":[236,112,71.5,68.5],"area":4897.75,"segmentation":[],"iscrowd":0},{"id":67,"image_id":30,"category_id":2,"bbox":[116,164,214,163],"area":34882,"segmentation":[],"iscrowd":0},{"id":68,"image_id":31,"category_id":2,"bbox":[64,68,253,191],"area":48323,"segmentation":[],"iscrowd":0},{"id":69,"image_id":32,"category_id":4,"bbox":[148,58,190,254],"area":48260,"segmentation":[],"iscrowd":0},{"id":70,"image_id":32,"category_id":4,"bbox":[171,23,28.5,93],"area":2650.5,"segmentation":[],"iscrowd":0},{"id":71,"image_id":32,"category_id":4,"bbox":[229,148,82,79.5],"area":6519,"segmentation":[],"iscrowd":0},{"id":72,"image_id":32,"category_id":4,"bbox":[149,145,38,122.5],"area":4655,"segmentation":[],"iscrowd":0},{"id":73,"image_id":32,"category_id":4,"bbox":[243,128,84.5,19],"area":1605.5,"segmentation":[],"iscrowd":0},{"id":74,"image_id":33,"category_id":4,"bbox":[41,81,276.5,159],"area":43963.5,"segmentation":[],"iscrowd":0},{"id":75,"image_id":33,"category_id":4,"bbox":[143,57,30.5,71.5],"area":2180.75,"segmentation":[],"iscrowd":0},{"id":76,"image_id":33,"category_id":4,"bbox":[258,52,14.5,41.5],"area":601.75,"segmentation":[],"iscrowd":0},{"id":77,"image_id":33,"category_id":4,"bbox":[138,252,107,56.5],"area":6045.5,"segmentation":[],"iscrowd":0},{"id":78,"image_id":34,"category_id":2,"bbox":[128,95,165.5,130],"area":21515,"segmentation":[],"iscrowd":0},{"id":79,"image_id":35,"category_id":4,"bbox":[102,82,243.5,229.5],"area":55883.25,"segmentation":[],"iscrowd":0},{"id":80,"image_id":35,"category_id":4,"bbox":[167,54,12,42.5],"area":510,"segmentation":[],"iscrowd":0},{"id":81,"image_id":35,"category_id":4,"bbox":[261,62,10.5,38],"area":399,"segmentation":[],"iscrowd":0},{"id":82,"image_id":35,"category_id":4,"bbox":[275,100,1,2.5],"area":2.5,"segmentation":[],"iscrowd":0},{"id":83,"image_id":36,"category_id":2,"bbox":[143,132,151.5,113],"area":17119.5,"segmentation":[],"iscrowd":0},{"id":84,"image_id":37,"category_id":2,"bbox":[150,101,194.5,145],"area":28202.5,"segmentation":[],"iscrowd":0},{"id":85,"image_id":38,"category_id":2,"bbox":[142,85,143,107.5],"area":15372.5,"segmentation":[],"iscrowd":0},{"id":86,"image_id":39,"category_id":3,"bbox":[117,72,154.5,158.5],"area":24488.25,"segmentation":[],"iscrowd":0},{"id":87,"image_id":40,"category_id":1,"bbox":[89,16,269,348],"area":93612,"segmentation":[],"iscrowd":0},{"id":88,"image_id":40,"category_id":1,"bbox":[190,165,86.5,26],"area":2249,"segmentation":[],"iscrowd":0},{"id":89,"image_id":40,"category_id":1,"bbox":[286,257,39,17.5],"area":682.5,"segmentation":[],"iscrowd":0},{"id":90,"image_id":41,"category_id":2,"bbox":[161,160,139,104.5],"area":14525.5,"segmentation":[],"iscrowd":0},{"id":91,"image_id":42,"category_id":4,"bbox":[108,5,224,328.5],"area":73584,"segmentation":[],"iscrowd":0},{"id":92,"image_id":42,"category_id":4,"bbox":[234,121,95,84.5],"area":8027.5,"segmentation":[],"iscrowd":0},{"id":93,"image_id":43,"category_id":3,"bbox":[207,91,130,144.5],"area":18785,"segmentation":[],"iscrowd":0},{"id":94,"image_id":44,"category_id":4,"bbox":[150,79,200,239.5],"area":47900,"segmentation":[],"iscrowd":0},{"id":95,"image_id":44,"category_id":4,"bbox":[265,79,34.5,35.5],"area":1224.75,"segmentation":[],"iscrowd":0},{"id":96,"image_id":44,"category_id":4,"bbox":[305,50,20.5,62.5],"area":1281.25,"segmentation":[],"iscrowd":0},{"id":97,"image_id":44,"category_id":4,"bbox":[210,63,51.5,61],"area":3141.5,"segmentation":[],"iscrowd":0},{"id":98,"image_id":45,"category_id":1,"bbox":[112,10,166,359.5],"area":59677,"segmentation":[],"iscrowd":0},{"id":99,"image_id":45,"category_id":1,"bbox":[236,238,77.5,68.5],"area":5308.75,"segmentation":[],"iscrowd":0},{"id":100,"image_id":46,"category_id":2,"bbox":[165,113,173,131],"area":22663,"segmentation":[],"iscrowd":0},{"id":101,"image_id":47,"category_id":1,"bbox":[95,78,214.5,188],"area":40326,"segmentation":[],"iscrowd":0},{"id":102,"image_id":47,"category_id":1,"bbox":[190,191,38.5,9.5],"area":365.75,"segmentation":[],"iscrowd":0},{"id":103,"image_id":47,"category_id":1,"bbox":[157,198,71.5,15.5],"area":1108.25,"segmentation":[],"iscrowd":0},{"id":104,"image_id":47,"category_id":1,"bbox":[108,260,121.5,90.5],"area":10995.75,"segmentation":[],"iscrowd":0},{"id":105,"image_id":47,"category_id":1,"bbox":[230,292,35.5,70.5],"area":2502.75,"segmentation":[],"iscrowd":0},{"id":106,"image_id":47,"category_id":1,"bbox":[232,275,31.5,17.5],"area":551.25,"segmentation":[],"iscrowd":0},{"id":107,"image_id":48,"category_id":2,"bbox":[137,94,225.5,170],"area":38335,"segmentation":[],"iscrowd":0},{"id":108,"image_id":49,"category_id":1,"bbox":[107,79,195,297.5],"area":58012.5,"segmentation":[],"iscrowd":0},{"id":109,"image_id":49,"category_id":1,"bbox":[181,208,82.5,22.5],"area":1856.25,"segmentation":[],"iscrowd":0},{"id":110,"image_id":49,"category_id":1,"bbox":[185,271,133.5,85],"area":11347.5,"segmentation":[],"iscrowd":0},{"id":111,"image_id":49,"category_id":1,"bbox":[139,306,86,88.5],"area":7611,"segmentation":[],"iscrowd":0},{"id":112,"image_id":49,"category_id":1,"bbox":[241,276,47.5,17.5],"area":831.25,"segmentation":[],"iscrowd":0},{"id":113,"image_id":50,"category_id":4,"bbox":[109,82,203.5,135.5],"area":27574.25,"segmentation":[],"iscrowd":0},{"id":114,"image_id":50,"category_id":4,"bbox":[175,221,78.5,28],"area":2198,"segmentation":[],"iscrowd":0},{"id":115,"image_id":50,"category_id":4,"bbox":[267,104,5,2.5],"area":12.5,"segmentation":[],"iscrowd":0},{"id":116,"image_id":51,"category_id":4,"bbox":[27,39,361.5,212],"area":76638,"segmentation":[],"iscrowd":0},{"id":117,"image_id":51,"category_id":4,"bbox":[116,45,24,63],"area":1512,"segmentation":[],"iscrowd":0},{"id":118,"image_id":51,"category_id":4,"bbox":[155,266,117,62.5],"area":7312.5,"segmentation":[],"iscrowd":0},{"id":119,"image_id":52,"category_id":3,"bbox":[161,121,87,90.5],"area":7873.5,"segmentation":[],"iscrowd":0},{"id":120,"image_id":53,"category_id":1,"bbox":[96,77,208.5,224],"area":46704,"segmentation":[],"iscrowd":0},{"id":121,"image_id":53,"category_id":1,"bbox":[181,196,74.5,29],"area":2160.5,"segmentation":[],"iscrowd":0},{"id":122,"image_id":53,"category_id":1,"bbox":[176,265,133.5,89],"area":11881.5,"segmentation":[],"iscrowd":0},{"id":123,"image_id":53,"category_id":1,"bbox":[146,287,74.5,69.5],"area":5177.75,"segmentation":[],"iscrowd":0},{"id":124,"image_id":54,"category_id":2,"bbox":[131,76,194.5,150],"area":29175,"segmentation":[],"iscrowd":0},{"id":125,"image_id":55,"category_id":1,"bbox":[116,95,218.5,298],"area":65113,"segmentation":[],"iscrowd":0},{"id":126,"image_id":55,"category_id":1,"bbox":[201,230,82,25.5],"area":2091,"segmentation":[],"iscrowd":0},{"id":127,"image_id":55,"category_id":1,"bbox":[162,324,49,55],"area":2695,"segmentation":[],"iscrowd":0},{"id":128,"image_id":55,"category_id":1,"bbox":[177,371,51,40],"area":2040,"segmentation":[],"iscrowd":0},{"id":129,"image_id":55,"category_id":1,"bbox":[297,35,5,4.5],"area":22.5,"segmentation":[],"iscrowd":0},{"id":130,"image_id":56,"category_id":2,"bbox":[128,179,191,145.5],"area":27790.5,"segmentation":[],"iscrowd":0},{"id":131,"image_id":57,"category_id":3,"bbox":[183,136,121,126.5],"area":15306.5,"segmentation":[],"iscrowd":0},{"id":132,"image_id":58,"category_id":2,"bbox":[172,153,166.5,124.5],"area":20729.25,"segmentation":[],"iscrowd":0},{"id":133,"image_id":59,"category_id":1,"bbox":[118,56,233.5,288],"area":67248,"segmentation":[],"iscrowd":0},{"id":134,"image_id":59,"category_id":1,"bbox":[217,346,60.5,35],"area":2117.5,"segmentation":[],"iscrowd":0},{"id":135,"image_id":59,"category_id":1,"bbox":[187,302,53.5,26],"area":1391,"segmentation":[],"iscrowd":0},{"id":136,"image_id":60,"category_id":4,"bbox":[112,75,178.5,138.5],"area":24722.25,"segmentation":[],"iscrowd":0},{"id":137,"image_id":60,"category_id":4,"bbox":[195,60,23,43.5],"area":1000.5,"segmentation":[],"iscrowd":0},{"id":138,"image_id":60,"category_id":4,"bbox":[271,65,14,35.5],"area":497,"segmentation":[],"iscrowd":0},{"id":139,"image_id":60,"category_id":4,"bbox":[171,204,70,28],"area":1960,"segmentation":[],"iscrowd":0},{"id":140,"image_id":61,"category_id":1,"bbox":[117,64,245.5,325.5],"area":79910.25,"segmentation":[],"iscrowd":0},{"id":141,"image_id":61,"category_id":1,"bbox":[280,281,71,106],"area":7526,"segmentation":[],"iscrowd":0},{"id":142,"image_id":61,"category_id":1,"bbox":[194,204,84.5,21.5],"area":1816.75,"segmentation":[],"iscrowd":0},{"id":143,"image_id":62,"category_id":1,"bbox":[74,5,246.5,365],"area":89972.5,"segmentation":[],"iscrowd":0},{"id":144,"image_id":62,"category_id":1,"bbox":[183,170,74,21.5],"area":1591,"segmentation":[],"iscrowd":0},{"id":145,"image_id":63,"category_id":4,"bbox":[73,51,221,154],"area":34034,"segmentation":[],"iscrowd":0},{"id":146,"image_id":63,"category_id":4,"bbox":[107,46,12.5,27],"area":337.5,"segmentation":[],"iscrowd":0},{"id":147,"image_id":63,"category_id":4,"bbox":[144,213,89,42],"area":3738,"segmentation":[],"iscrowd":0},{"id":148,"image_id":64,"category_id":4,"bbox":[116,112,182.5,210.5],"area":38416.25,"segmentation":[],"iscrowd":0},{"id":149,"image_id":64,"category_id":4,"bbox":[97,103,43,42],"area":1806,"segmentation":[],"iscrowd":0},{"id":150,"image_id":64,"category_id":4,"bbox":[204,72,21.5,47.5],"area":1021.25,"segmentation":[],"iscrowd":0},{"id":151,"image_id":64,"category_id":4,"bbox":[272,71,25,73],"area":1825,"segmentation":[],"iscrowd":0},{"id":152,"image_id":65,"category_id":1,"bbox":[70,22,132,293.5],"area":38742,"segmentation":[],"iscrowd":0},{"id":153,"image_id":65,"category_id":1,"bbox":[102,159,83.5,14],"area":1169,"segmentation":[],"iscrowd":0},{"id":154,"image_id":65,"category_id":1,"bbox":[174,234,72,80],"area":5760,"segmentation":[],"iscrowd":0},{"id":155,"image_id":65,"category_id":1,"bbox":[150,19,85.5,31.5],"area":2693.25,"segmentation":[],"iscrowd":0},{"id":156,"image_id":65,"category_id":1,"bbox":[29,7,49.5,17],"area":841.5,"segmentation":[],"iscrowd":0},{"id":157,"image_id":66,"category_id":4,"bbox":[129,19,190.5,305.5],"area":58197.75,"segmentation":[],"iscrowd":0},{"id":158,"image_id":66,"category_id":4,"bbox":[118,201,27,74],"area":1998,"segmentation":[],"iscrowd":0},{"id":159,"image_id":66,"category_id":4,"bbox":[280,137,47,82],"area":3854,"segmentation":[],"iscrowd":0},{"id":160,"image_id":67,"category_id":2,"bbox":[132,88,188,143.5],"area":26978,"segmentation":[],"iscrowd":0},{"id":161,"image_id":68,"category_id":4,"bbox":[117,60,124,133.5],"area":16554,"segmentation":[],"iscrowd":0},{"id":162,"image_id":68,"category_id":4,"bbox":[235,42,60,66],"area":3960,"segmentation":[],"iscrowd":0},{"id":163,"image_id":68,"category_id":4,"bbox":[124,134,204,215],"area":43860,"segmentation":[],"iscrowd":0},{"id":164,"image_id":69,"category_id":2,"bbox":[171,118,179,131.5],"area":23538.5,"segmentation":[],"iscrowd":0},{"id":165,"image_id":70,"category_id":3,"bbox":[77,108,221,196],"area":43316,"segmentation":[],"iscrowd":0},{"id":166,"image_id":71,"category_id":4,"bbox":[98,103,180.5,149.5],"area":26984.75,"segmentation":[],"iscrowd":0},{"id":167,"image_id":71,"category_id":4,"bbox":[192,78,15.5,42.5],"area":658.75,"segmentation":[],"iscrowd":0},{"id":168,"image_id":71,"category_id":4,"bbox":[274,76,15.5,48],"area":744,"segmentation":[],"iscrowd":0},{"id":169,"image_id":71,"category_id":4,"bbox":[266,107,18.5,12.5],"area":231.25,"segmentation":[],"iscrowd":0},{"id":170,"image_id":71,"category_id":4,"bbox":[151,232,82.5,33],"area":2722.5,"segmentation":[],"iscrowd":0},{"id":171,"image_id":72,"category_id":1,"bbox":[117,80,230,275.5],"area":63365,"segmentation":[],"iscrowd":0},{"id":172,"image_id":72,"category_id":1,"bbox":[209,209,70,28.5],"area":1995,"segmentation":[],"iscrowd":0},{"id":173,"image_id":72,"category_id":1,"bbox":[213,357,61.5,32.5],"area":1998.75,"segmentation":[],"iscrowd":0},{"id":174,"image_id":73,"category_id":4,"bbox":[124,42,219.5,284],"area":62338,"segmentation":[],"iscrowd":0},{"id":175,"image_id":73,"category_id":4,"bbox":[314,17,36.5,102],"area":3723,"segmentation":[],"iscrowd":0},{"id":176,"image_id":73,"category_id":4,"bbox":[246,39,13,29.5],"area":383.5,"segmentation":[],"iscrowd":0},{"id":177,"image_id":74,"category_id":3,"bbox":[165,127,142,165],"area":23430,"segmentation":[],"iscrowd":0},{"id":178,"image_id":75,"category_id":3,"bbox":[145,151,124,119],"area":14756,"segmentation":[],"iscrowd":0},{"id":179,"image_id":76,"category_id":3,"bbox":[159,171,98.5,110],"area":10835,"segmentation":[],"iscrowd":0},{"id":180,"image_id":77,"category_id":2,"bbox":[111,125,218.5,167.5],"area":36598.75,"segmentation":[],"iscrowd":0},{"id":181,"image_id":78,"category_id":1,"bbox":[86,74,221,288],"area":63648,"segmentation":[],"iscrowd":0},{"id":182,"image_id":78,"category_id":1,"bbox":[163,197,72,19],"area":1368,"segmentation":[],"iscrowd":0},{"id":183,"image_id":78,"category_id":1,"bbox":[216,239,73.5,116.5],"area":8562.75,"segmentation":[],"iscrowd":0},{"id":184,"image_id":79,"category_id":2,"bbox":[72,149,225,171.5],"area":38587.5,"segmentation":[],"iscrowd":0},{"id":185,"image_id":80,"category_id":4,"bbox":[151,123,161.5,155.5],"area":25113.25,"segmentation":[],"iscrowd":0},{"id":186,"image_id":80,"category_id":4,"bbox":[250,97,118,124.5],"area":14691,"segmentation":[],"iscrowd":0},{"id":187,"image_id":80,"category_id":4,"bbox":[183,243,83.5,78],"area":6513,"segmentation":[],"iscrowd":0},{"id":188,"image_id":81,"category_id":2,"bbox":[151,167,172.5,130],"area":22425,"segmentation":[],"iscrowd":0},{"id":189,"image_id":82,"category_id":4,"bbox":[115,20,246.5,315.5],"area":77770.75,"segmentation":[],"iscrowd":0},{"id":190,"image_id":82,"category_id":4,"bbox":[257,15,70,99.5],"area":6965,"segmentation":[],"iscrowd":0},{"id":191,"image_id":82,"category_id":4,"bbox":[305,148,31.5,70],"area":2205,"segmentation":[],"iscrowd":0},{"id":192,"image_id":83,"category_id":1,"bbox":[81,43,229.5,290.5],"area":66669.75,"segmentation":[],"iscrowd":0},{"id":193,"image_id":83,"category_id":1,"bbox":[180,180,77,26],"area":2002,"segmentation":[],"iscrowd":0},{"id":194,"image_id":83,"category_id":1,"bbox":[143,270,66.5,83.5],"area":5552.75,"segmentation":[],"iscrowd":0},{"id":195,"image_id":84,"category_id":1,"bbox":[144,18,160,340],"area":54400,"segmentation":[],"iscrowd":0},{"id":196,"image_id":84,"category_id":1,"bbox":[263,248,78.5,67.5],"area":5298.75,"segmentation":[],"iscrowd":0},{"id":197,"image_id":85,"category_id":2,"bbox":[90,133,222,166.5],"area":36963,"segmentation":[],"iscrowd":0},{"id":198,"image_id":86,"category_id":3,"bbox":[138,106,120,141.5],"area":16980,"segmentation":[],"iscrowd":0},{"id":199,"image_id":87,"category_id":4,"bbox":[173,60,183.5,275],"area":50462.5,"segmentation":[],"iscrowd":0},{"id":200,"image_id":87,"category_id":4,"bbox":[312,32,26,64.5],"area":1677,"segmentation":[],"iscrowd":0},{"id":201,"image_id":88,"category_id":2,"bbox":[110,170,200.5,151],"area":30275.5,"segmentation":[],"iscrowd":0},{"id":202,"image_id":89,"category_id":1,"bbox":[125,11,205,340.5],"area":69802.5,"segmentation":[],"iscrowd":0},{"id":203,"image_id":89,"category_id":1,"bbox":[237,171,39.5,14],"area":553,"segmentation":[],"iscrowd":0},{"id":204,"image_id":89,"category_id":1,"bbox":[242,244,64.5,33.5],"area":2160.75,"segmentation":[],"iscrowd":0},{"id":205,"image_id":90,"category_id":4,"bbox":[100,27,197.5,286.5],"area":56583.75,"segmentation":[],"iscrowd":0},{"id":206,"image_id":90,"category_id":4,"bbox":[256,28,43,72],"area":3096,"segmentation":[],"iscrowd":0},{"id":207,"image_id":90,"category_id":4,"bbox":[280,143,31.5,190.5],"area":6000.75,"segmentation":[],"iscrowd":0},{"id":208,"image_id":91,"category_id":4,"bbox":[135,40,179.5,230.5],"area":41374.75,"segmentation":[],"iscrowd":0},{"id":209,"image_id":91,"category_id":4,"bbox":[263,29,27,75],"area":2025,"segmentation":[],"iscrowd":0},{"id":210,"image_id":92,"category_id":2,"bbox":[117,86,188.5,144],"area":27144,"segmentation":[],"iscrowd":0},{"id":211,"image_id":93,"category_id":2,"bbox":[166,137,133.5,100],"area":13350,"segmentation":[],"iscrowd":0},{"id":212,"image_id":94,"category_id":4,"bbox":[150,44,215.5,280],"area":60340,"segmentation":[],"iscrowd":0},{"id":213,"image_id":94,"category_id":4,"bbox":[299,29,43.5,89],"area":3871.5,"segmentation":[],"iscrowd":0},{"id":214,"image_id":95,"category_id":1,"bbox":[108,70,215,227.5],"area":48912.5,"segmentation":[],"iscrowd":0},{"id":215,"image_id":95,"category_id":1,"bbox":[184,200,79,20],"area":1580,"segmentation":[],"iscrowd":0},{"id":216,"image_id":95,"category_id":1,"bbox":[220,235,93,114.5],"area":10648.5,"segmentation":[],"iscrowd":0},{"id":217,"image_id":95,"category_id":1,"bbox":[155,291,42,77],"area":3234,"segmentation":[],"iscrowd":0},{"id":218,"image_id":96,"category_id":4,"bbox":[177,43,119.5,185],"area":22107.5,"segmentation":[],"iscrowd":0},{"id":219,"image_id":96,"category_id":4,"bbox":[292,23,38.5,94.5],"area":3638.25,"segmentation":[],"iscrowd":0},{"id":220,"image_id":96,"category_id":4,"bbox":[145,131,221,200.5],"area":44310.5,"segmentation":[],"iscrowd":0},{"id":221,"image_id":96,"category_id":4,"bbox":[221,186,34,28],"area":952,"segmentation":[],"iscrowd":0},{"id":222,"image_id":97,"category_id":3,"bbox":[152,130,118.5,111.5],"area":13212.75,"segmentation":[],"iscrowd":0},{"id":223,"image_id":98,"category_id":2,"bbox":[126,96,228.5,171],"area":39073.5,"segmentation":[],"iscrowd":0},{"id":224,"image_id":99,"category_id":4,"bbox":[32,81,227.5,110.5],"area":25138.75,"segmentation":[],"iscrowd":0},{"id":225,"image_id":99,"category_id":4,"bbox":[66,47,18,36],"area":648,"segmentation":[],"iscrowd":0},{"id":226,"image_id":99,"category_id":4,"bbox":[173,52,20,68.5],"area":1370,"segmentation":[],"iscrowd":0},{"id":227,"image_id":99,"category_id":4,"bbox":[91,176,124.5,55.5],"area":6909.75,"segmentation":[],"iscrowd":0},{"id":228,"image_id":99,"category_id":4,"bbox":[126,236,98,50],"area":4900,"segmentation":[],"iscrowd":0},{"id":229,"image_id":100,"category_id":2,"bbox":[90,39,279.5,217],"area":60651.5,"segmentation":[],"iscrowd":0},{"id":230,"image_id":101,"category_id":3,"bbox":[166,114,116.5,133.5],"area":15552.75,"segmentation":[],"iscrowd":0},{"id":231,"image_id":102,"category_id":4,"bbox":[109,37,180.5,158],"area":28519,"segmentation":[],"iscrowd":0},{"id":232,"image_id":102,"category_id":4,"bbox":[138,36,14,32],"area":448,"segmentation":[],"iscrowd":0},{"id":233,"image_id":102,"category_id":4,"bbox":[170,202,80.5,31.5],"area":2535.75,"segmentation":[],"iscrowd":0},{"id":234,"image_id":102,"category_id":4,"bbox":[275,73,44.5,38],"area":1691,"segmentation":[],"iscrowd":0},{"id":235,"image_id":103,"category_id":4,"bbox":[127,43,171.5,254.5],"area":43646.75,"segmentation":[],"iscrowd":0},{"id":236,"image_id":103,"category_id":4,"bbox":[250,128,61.5,72.5],"area":4458.75,"segmentation":[],"iscrowd":0},{"id":237,"image_id":104,"category_id":3,"bbox":[168,81,128,138.5],"area":17728,"segmentation":[],"iscrowd":0},{"id":238,"image_id":105,"category_id":3,"bbox":[192,107,134,159],"area":21306,"segmentation":[],"iscrowd":0},{"id":239,"image_id":106,"category_id":4,"bbox":[176,27,163.5,273.5],"area":44717.25,"segmentation":[],"iscrowd":0},{"id":240,"image_id":106,"category_id":4,"bbox":[120,26,208,124.5],"area":25896,"segmentation":[],"iscrowd":0},{"id":241,"image_id":107,"category_id":1,"bbox":[125,11,251.5,331.5],"area":83372.25,"segmentation":[],"iscrowd":0},{"id":242,"image_id":107,"category_id":1,"bbox":[222,351,77.5,28],"area":2170,"segmentation":[],"iscrowd":0},{"id":243,"image_id":107,"category_id":1,"bbox":[229,334,51.5,29.5],"area":1519.25,"segmentation":[],"iscrowd":0},{"id":244,"image_id":108,"category_id":2,"bbox":[96,156,197,147],"area":28959,"segmentation":[],"iscrowd":0},{"id":245,"image_id":109,"category_id":2,"bbox":[88,101,296,221.5],"area":65564,"segmentation":[],"iscrowd":0},{"id":246,"image_id":110,"category_id":2,"bbox":[151,159,189.5,140],"area":26530,"segmentation":[],"iscrowd":0},{"id":247,"image_id":111,"category_id":3,"bbox":[149,127,123.5,143.5],"area":17722.25,"segmentation":[],"iscrowd":0},{"id":248,"image_id":112,"category_id":2,"bbox":[125,97,179.5,137.5],"area":24681.25,"segmentation":[],"iscrowd":0},{"id":249,"image_id":113,"category_id":3,"bbox":[156,105,118,141],"area":16638,"segmentation":[],"iscrowd":0},{"id":250,"image_id":114,"category_id":2,"bbox":[150,127,166,124],"area":20584,"segmentation":[],"iscrowd":0},{"id":251,"image_id":115,"category_id":4,"bbox":[118,64,197.5,215],"area":42462.5,"segmentation":[],"iscrowd":0},{"id":252,"image_id":115,"category_id":4,"bbox":[207,79,13,22.5],"area":292.5,"segmentation":[],"iscrowd":0},{"id":253,"image_id":115,"category_id":4,"bbox":[181,66,11,40],"area":440,"segmentation":[],"iscrowd":0},{"id":254,"image_id":115,"category_id":4,"bbox":[265,65,10,40],"area":400,"segmentation":[],"iscrowd":0},{"id":255,"image_id":115,"category_id":4,"bbox":[206,65,0.5,0.5],"area":0.25,"segmentation":[],"iscrowd":0},{"id":256,"image_id":116,"category_id":4,"bbox":[128,81,159,106.5],"area":16933.5,"segmentation":[],"iscrowd":0},{"id":257,"image_id":116,"category_id":4,"bbox":[170,193,66,22.5],"area":1485,"segmentation":[],"iscrowd":0},{"id":258,"image_id":116,"category_id":4,"bbox":[258,69,9.5,25],"area":237.5,"segmentation":[],"iscrowd":0},{"id":259,"image_id":116,"category_id":4,"bbox":[188,67,10,41],"area":410,"segmentation":[],"iscrowd":0},{"id":260,"image_id":117,"category_id":2,"bbox":[159,99,175.5,133],"area":23341.5,"segmentation":[],"iscrowd":0},{"id":261,"image_id":118,"category_id":4,"bbox":[123,102,232,252],"area":58464,"segmentation":[],"iscrowd":0},{"id":262,"image_id":118,"category_id":4,"bbox":[309,93,33.5,87],"area":2914.5,"segmentation":[],"iscrowd":0},{"id":263,"image_id":119,"category_id":2,"bbox":[130,116,160.5,119.5],"area":19179.75,"segmentation":[],"iscrowd":0},{"id":264,"image_id":120,"category_id":2,"bbox":[133,165,163,121.5],"area":19804.5,"segmentation":[],"iscrowd":0},{"id":265,"image_id":121,"category_id":1,"bbox":[98,90,214.5,278.5],"area":59738.25,"segmentation":[],"iscrowd":0},{"id":266,"image_id":121,"category_id":1,"bbox":[190,225,71,27],"area":1917,"segmentation":[],"iscrowd":0},{"id":267,"image_id":121,"category_id":1,"bbox":[157,323,85.5,79],"area":6754.5,"segmentation":[],"iscrowd":0},{"id":268,"image_id":122,"category_id":1,"bbox":[43,20,240.5,109.5],"area":26334.75,"segmentation":[],"iscrowd":0},{"id":269,"image_id":122,"category_id":1,"bbox":[204,244,46,82],"area":3772,"segmentation":[],"iscrowd":0},{"id":270,"image_id":122,"category_id":1,"bbox":[127,155,78.5,24],"area":1884,"segmentation":[],"iscrowd":0},{"id":271,"image_id":122,"category_id":1,"bbox":[84,234,62,94.5],"area":5859,"segmentation":[],"iscrowd":0},{"id":272,"image_id":122,"category_id":1,"bbox":[123,110,82.5,49.5],"area":4083.75,"segmentation":[],"iscrowd":0},{"id":273,"image_id":122,"category_id":1,"bbox":[130,183,135.5,51.5],"area":6978.25,"segmentation":[],"iscrowd":0},{"id":274,"image_id":123,"category_id":4,"bbox":[168,77,186,230],"area":42780,"segmentation":[],"iscrowd":0},{"id":275,"image_id":123,"category_id":4,"bbox":[311,50,29.5,76],"area":2242,"segmentation":[],"iscrowd":0},{"id":276,"image_id":123,"category_id":4,"bbox":[230,64,49.5,57],"area":2821.5,"segmentation":[],"iscrowd":0},{"id":277,"image_id":124,"category_id":4,"bbox":[90,119,83.5,93],"area":7765.5,"segmentation":[],"iscrowd":0},{"id":278,"image_id":124,"category_id":4,"bbox":[61,44,177.5,314],"area":55735,"segmentation":[],"iscrowd":0},{"id":279,"image_id":124,"category_id":4,"bbox":[202,109,137,167],"area":22879,"segmentation":[],"iscrowd":0},{"id":280,"image_id":124,"category_id":4,"bbox":[231,59,49,50],"area":2450,"segmentation":[],"iscrowd":0},{"id":281,"image_id":125,"category_id":4,"bbox":[149,160,110.5,56],"area":6188,"segmentation":[],"iscrowd":0},{"id":282,"image_id":125,"category_id":4,"bbox":[132,46,14.5,40.5],"area":587.25,"segmentation":[],"iscrowd":0},{"id":283,"image_id":125,"category_id":4,"bbox":[229,48,17,49],"area":833,"segmentation":[],"iscrowd":0},{"id":284,"image_id":125,"category_id":4,"bbox":[112,86,192.5,77],"area":14822.5,"segmentation":[],"iscrowd":0},{"id":285,"image_id":125,"category_id":4,"bbox":[288,81,49.5,41.5],"area":2054.25,"segmentation":[],"iscrowd":0},{"id":286,"image_id":125,"category_id":4,"bbox":[178,221,87,38],"area":3306,"segmentation":[],"iscrowd":0},{"id":287,"image_id":126,"category_id":4,"bbox":[101,34,238,314],"area":74732,"segmentation":[],"iscrowd":0},{"id":288,"image_id":126,"category_id":4,"bbox":[246,44,64.5,82],"area":5289,"segmentation":[],"iscrowd":0},{"id":289,"image_id":126,"category_id":4,"bbox":[112,192,51.5,184.5],"area":9501.75,"segmentation":[],"iscrowd":0},{"id":290,"image_id":127,"category_id":3,"bbox":[159,122,98,114.5],"area":11221,"segmentation":[],"iscrowd":0},{"id":291,"image_id":128,"category_id":2,"bbox":[167,124,159.5,119],"area":18980.5,"segmentation":[],"iscrowd":0},{"id":292,"image_id":129,"category_id":2,"bbox":[174,92,185,138.5],"area":25622.5,"segmentation":[],"iscrowd":0},{"id":293,"image_id":130,"category_id":1,"bbox":[127,92,206.5,225],"area":46462.5,"segmentation":[],"iscrowd":0},{"id":294,"image_id":130,"category_id":1,"bbox":[212,220,76.5,33],"area":2524.5,"segmentation":[],"iscrowd":0},{"id":295,"image_id":130,"category_id":1,"bbox":[172,311,77.5,41.5],"area":3216.25,"segmentation":[],"iscrowd":0},{"id":296,"image_id":130,"category_id":1,"bbox":[289,336,53,30],"area":1590,"segmentation":[],"iscrowd":0},{"id":297,"image_id":130,"category_id":1,"bbox":[262,296,55.5,24],"area":1332,"segmentation":[],"iscrowd":0},{"id":298,"image_id":130,"category_id":1,"bbox":[189,368,55,39],"area":2145,"segmentation":[],"iscrowd":0},{"id":299,"image_id":131,"category_id":2,"bbox":[115,171,200,151],"area":30200,"segmentation":[],"iscrowd":0},{"id":300,"image_id":132,"category_id":4,"bbox":[151,51,202,254.5],"area":51409,"segmentation":[],"iscrowd":0},{"id":301,"image_id":132,"category_id":4,"bbox":[292,39,34,79.5],"area":2703,"segmentation":[],"iscrowd":0},{"id":302,"image_id":133,"category_id":1,"bbox":[35,23,169,299],"area":50531,"segmentation":[],"iscrowd":0},{"id":303,"image_id":133,"category_id":1,"bbox":[117,156,75.5,16],"area":1208,"segmentation":[],"iscrowd":0},{"id":304,"image_id":133,"category_id":1,"bbox":[132,229,117,90.5],"area":10588.5,"segmentation":[],"iscrowd":0},{"id":305,"image_id":134,"category_id":2,"bbox":[115,83,202,157],"area":31714,"segmentation":[],"iscrowd":0},{"id":306,"image_id":135,"category_id":4,"bbox":[153,56,183.5,227.5],"area":41746.25,"segmentation":[],"iscrowd":0},{"id":307,"image_id":135,"category_id":4,"bbox":[282,48,30,70],"area":2100,"segmentation":[],"iscrowd":0},{"id":308,"image_id":136,"category_id":1,"bbox":[83,88,261.5,312],"area":81588,"segmentation":[],"iscrowd":0},{"id":309,"image_id":136,"category_id":1,"bbox":[187,230,90,20],"area":1800,"segmentation":[],"iscrowd":0},{"id":310,"image_id":136,"category_id":1,"bbox":[188,230,89,22.5],"area":2002.5,"segmentation":[],"iscrowd":0},{"id":311,"image_id":136,"category_id":1,"bbox":[146,309,178.5,91],"area":16243.5,"segmentation":[],"iscrowd":0},{"id":312,"image_id":136,"category_id":1,"bbox":[157,367,46,38.5],"area":1771,"segmentation":[],"iscrowd":0},{"id":313,"image_id":136,"category_id":1,"bbox":[191,195,37,16],"area":592,"segmentation":[],"iscrowd":0},{"id":314,"image_id":136,"category_id":1,"bbox":[150,181,7,12.5],"area":87.5,"segmentation":[],"iscrowd":0},{"id":315,"image_id":136,"category_id":1,"bbox":[148,207,25,114],"area":2850,"segmentation":[],"iscrowd":0},{"id":316,"image_id":137,"category_id":4,"bbox":[38,56,328.5,152],"area":49932,"segmentation":[],"iscrowd":0},{"id":317,"image_id":137,"category_id":4,"bbox":[269,54,23,59.5],"area":1368.5,"segmentation":[],"iscrowd":0},{"id":318,"image_id":137,"category_id":4,"bbox":[316,141,76,43],"area":3268,"segmentation":[],"iscrowd":0},{"id":319,"image_id":137,"category_id":4,"bbox":[144,197,138.5,53.5],"area":7409.75,"segmentation":[],"iscrowd":0},{"id":320,"image_id":137,"category_id":4,"bbox":[165,265,107.5,70],"area":7525,"segmentation":[],"iscrowd":0},{"id":321,"image_id":138,"category_id":1,"bbox":[72,91,271.5,303.5],"area":82400.25,"segmentation":[],"iscrowd":0},{"id":322,"image_id":138,"category_id":1,"bbox":[168,235,87,24.5],"area":2131.5,"segmentation":[],"iscrowd":0},{"id":323,"image_id":138,"category_id":1,"bbox":[120,324,41,75],"area":3075,"segmentation":[],"iscrowd":0},{"id":324,"image_id":139,"category_id":2,"bbox":[86,127,167,128],"area":21376,"segmentation":[],"iscrowd":0},{"id":325,"image_id":140,"category_id":2,"bbox":[113,91,239.5,181.5],"area":43469.25,"segmentation":[],"iscrowd":0},{"id":326,"image_id":141,"category_id":4,"bbox":[101,81,157.5,134.5],"area":21183.75,"segmentation":[],"iscrowd":0},{"id":327,"image_id":141,"category_id":4,"bbox":[129,43,13,39.5],"area":513.5,"segmentation":[],"iscrowd":0},{"id":328,"image_id":141,"category_id":4,"bbox":[227,48,17,49],"area":833,"segmentation":[],"iscrowd":0},{"id":329,"image_id":141,"category_id":4,"bbox":[284,82,51.5,45],"area":2317.5,"segmentation":[],"iscrowd":0},{"id":330,"image_id":141,"category_id":4,"bbox":[166,223,90.5,40],"area":3620,"segmentation":[],"iscrowd":0},{"id":331,"image_id":142,"category_id":3,"bbox":[166,124,131,157],"area":20567,"segmentation":[],"iscrowd":0},{"id":332,"image_id":143,"category_id":1,"bbox":[105,102,175,261],"area":45675,"segmentation":[],"iscrowd":0},{"id":333,"image_id":143,"category_id":1,"bbox":[89,80,224,24.5],"area":5488,"segmentation":[],"iscrowd":0},{"id":334,"image_id":143,"category_id":1,"bbox":[157,201,72,16],"area":1152,"segmentation":[],"iscrowd":0},{"id":335,"image_id":143,"category_id":1,"bbox":[221,267,41.5,100.5],"area":4170.75,"segmentation":[],"iscrowd":0},{"id":336,"image_id":144,"category_id":2,"bbox":[153,142,156,116.5],"area":18174,"segmentation":[],"iscrowd":0},{"id":337,"image_id":145,"category_id":4,"bbox":[137,55,194.5,250.5],"area":48722.25,"segmentation":[],"iscrowd":0},{"id":338,"image_id":145,"category_id":4,"bbox":[279,45,29,77.5],"area":2247.5,"segmentation":[],"iscrowd":0},{"id":339,"image_id":146,"category_id":4,"bbox":[151,7,256.5,367],"area":94135.5,"segmentation":[],"iscrowd":0},{"id":340,"image_id":146,"category_id":4,"bbox":[313,12,65,64.5],"area":4192.5,"segmentation":[],"iscrowd":0},{"id":341,"image_id":146,"category_id":4,"bbox":[290,134,91,96],"area":8736,"segmentation":[],"iscrowd":0},{"id":342,"image_id":147,"category_id":2,"bbox":[127,89,194,147.5],"area":28615,"segmentation":[],"iscrowd":0},{"id":343,"image_id":148,"category_id":4,"bbox":[143,103,209,112],"area":23408,"segmentation":[],"iscrowd":0},{"id":344,"image_id":148,"category_id":4,"bbox":[138,41,16.5,59.5],"area":981.75,"segmentation":[],"iscrowd":0},{"id":345,"image_id":148,"category_id":4,"bbox":[252,42,23.5,69.5],"area":1633.25,"segmentation":[],"iscrowd":0},{"id":346,"image_id":148,"category_id":4,"bbox":[159,228,93.5,50],"area":4675,"segmentation":[],"iscrowd":0},{"id":347,"image_id":148,"category_id":4,"bbox":[75,111,59.5,39.5],"area":2350.25,"segmentation":[],"iscrowd":0},{"id":348,"image_id":148,"category_id":4,"bbox":[142,108,124,44.5],"area":5518,"segmentation":[],"iscrowd":0},{"id":349,"image_id":149,"category_id":2,"bbox":[128,172,197.5,149.5],"area":29526.25,"segmentation":[],"iscrowd":0},{"id":350,"image_id":150,"category_id":2,"bbox":[137,118,187.5,139.5],"area":26156.25,"segmentation":[],"iscrowd":0},{"id":351,"image_id":151,"category_id":4,"bbox":[131,90,212.5,239],"area":50787.5,"segmentation":[],"iscrowd":0},{"id":352,"image_id":151,"category_id":4,"bbox":[281,64,41,74.5],"area":3054.5,"segmentation":[],"iscrowd":0},{"id":353,"image_id":152,"category_id":4,"bbox":[116,106,203.5,208.5],"area":42429.75,"segmentation":[],"iscrowd":0},{"id":354,"image_id":152,"category_id":4,"bbox":[217,73,36.5,64.5],"area":2354.25,"segmentation":[],"iscrowd":0},{"id":355,"image_id":152,"category_id":4,"bbox":[270,82,28.5,60],"area":1710,"segmentation":[],"iscrowd":0},{"id":356,"image_id":152,"category_id":4,"bbox":[290,138,27,41.5],"area":1120.5,"segmentation":[],"iscrowd":0},{"id":357,"image_id":153,"category_id":2,"bbox":[85,91,204.5,155],"area":31697.5,"segmentation":[],"iscrowd":0},{"id":358,"image_id":154,"category_id":2,"bbox":[92,121,225,170],"area":38250,"segmentation":[],"iscrowd":0},{"id":359,"image_id":155,"category_id":2,"bbox":[133,121,176,133],"area":23408,"segmentation":[],"iscrowd":0},{"id":360,"image_id":155,"category_id":2,"bbox":[272,238,10,8.5],"area":85,"segmentation":[],"iscrowd":0},{"id":361,"image_id":156,"category_id":2,"bbox":[111,164,172,128.5],"area":22102,"segmentation":[],"iscrowd":0},{"id":362,"image_id":157,"category_id":3,"bbox":[182,84,126.5,148],"area":18722,"segmentation":[],"iscrowd":0},{"id":363,"image_id":158,"category_id":4,"bbox":[169,55,181.5,227],"area":41200.5,"segmentation":[],"iscrowd":0},{"id":364,"image_id":158,"category_id":4,"bbox":[307,44,24.5,49],"area":1200.5,"segmentation":[],"iscrowd":0},{"id":365,"image_id":159,"category_id":4,"bbox":[165,26,189,293],"area":55377,"segmentation":[],"iscrowd":0},{"id":366,"image_id":159,"category_id":4,"bbox":[284,8,40,98.5],"area":3940,"segmentation":[],"iscrowd":0},{"id":367,"image_id":159,"category_id":4,"bbox":[132,202,113,65],"area":7345,"segmentation":[],"iscrowd":0},{"id":368,"image_id":160,"category_id":3,"bbox":[164,107,90.5,105.5],"area":9547.75,"segmentation":[],"iscrowd":0},{"id":369,"image_id":161,"category_id":1,"bbox":[102,90,89,69],"area":6141,"segmentation":[],"iscrowd":0},{"id":370,"image_id":161,"category_id":1,"bbox":[144,193,88.5,31.5],"area":2787.75,"segmentation":[],"iscrowd":0},{"id":371,"image_id":161,"category_id":1,"bbox":[234,270,42,97],"area":4074,"segmentation":[],"iscrowd":0},{"id":372,"image_id":161,"category_id":1,"bbox":[113,266,67.5,82],"area":5535,"segmentation":[],"iscrowd":0},{"id":373,"image_id":162,"category_id":2,"bbox":[96,78,234.5,178.5],"area":41858.25,"segmentation":[],"iscrowd":0},{"id":374,"image_id":163,"category_id":2,"bbox":[152,106,179,133.5],"area":23896.5,"segmentation":[],"iscrowd":0},{"id":375,"image_id":164,"category_id":4,"bbox":[96,163,201.5,145],"area":29217.5,"segmentation":[],"iscrowd":0},{"id":376,"image_id":164,"category_id":4,"bbox":[202,131,22,48.5],"area":1067,"segmentation":[],"iscrowd":0},{"id":377,"image_id":164,"category_id":4,"bbox":[275,143,23.5,70.5],"area":1656.75,"segmentation":[],"iscrowd":0},{"id":378,"image_id":164,"category_id":4,"bbox":[175,305,36.5,9],"area":328.5,"segmentation":[],"iscrowd":0},{"id":379,"image_id":164,"category_id":4,"bbox":[173,273,14.5,8.5],"area":123.25,"segmentation":[],"iscrowd":0},{"id":380,"image_id":165,"category_id":4,"bbox":[143,46,190,258.5],"area":49115,"segmentation":[],"iscrowd":0},{"id":381,"image_id":165,"category_id":4,"bbox":[183,134,41,54.5],"area":2234.5,"segmentation":[],"iscrowd":0},{"id":382,"image_id":166,"category_id":3,"bbox":[154,113,123.5,144],"area":17784,"segmentation":[],"iscrowd":0},{"id":383,"image_id":167,"category_id":1,"bbox":[48,10,255.5,328],"area":83804,"segmentation":[],"iscrowd":0},{"id":384,"image_id":167,"category_id":1,"bbox":[111,271,78,78],"area":6084,"segmentation":[],"iscrowd":0},{"id":385,"image_id":167,"category_id":1,"bbox":[151,174,91.5,21.5],"area":1967.25,"segmentation":[],"iscrowd":0},{"id":386,"image_id":168,"category_id":3,"bbox":[165,97,110,134],"area":14740,"segmentation":[],"iscrowd":0},{"id":387,"image_id":169,"category_id":3,"bbox":[184,124,129,138],"area":17802,"segmentation":[],"iscrowd":0},{"id":388,"image_id":170,"category_id":4,"bbox":[162,48,13,50.5],"area":656.5,"segmentation":[],"iscrowd":0},{"id":389,"image_id":170,"category_id":4,"bbox":[94,88,49,40],"area":1960,"segmentation":[],"iscrowd":0},{"id":390,"image_id":170,"category_id":4,"bbox":[265,53,17,50],"area":850,"segmentation":[],"iscrowd":0},{"id":391,"image_id":170,"category_id":4,"bbox":[286,89,51.5,48.5],"area":2497.75,"segmentation":[],"iscrowd":0},{"id":392,"image_id":170,"category_id":4,"bbox":[158,224,94,39],"area":3666,"segmentation":[],"iscrowd":0},{"id":393,"image_id":170,"category_id":4,"bbox":[153,168,114,44.5],"area":5073,"segmentation":[],"iscrowd":0},{"id":394,"image_id":170,"category_id":4,"bbox":[160,112,114,46],"area":5244,"segmentation":[],"iscrowd":0},{"id":395,"image_id":171,"category_id":4,"bbox":[147,48,226.5,285],"area":64552.5,"segmentation":[],"iscrowd":0},{"id":396,"image_id":171,"category_id":4,"bbox":[325,35,24.5,62.5],"area":1531.25,"segmentation":[],"iscrowd":0},{"id":397,"image_id":171,"category_id":4,"bbox":[193,143,46,48],"area":2208,"segmentation":[],"iscrowd":0},{"id":398,"image_id":172,"category_id":2,"bbox":[117,171,159.5,119],"area":18980.5,"segmentation":[],"iscrowd":0},{"id":399,"image_id":173,"category_id":3,"bbox":[172,135,96.5,115.5],"area":11145.75,"segmentation":[],"iscrowd":0},{"id":400,"image_id":174,"category_id":1,"bbox":[110,97,242.5,306],"area":74205,"segmentation":[],"iscrowd":0},{"id":401,"image_id":174,"category_id":1,"bbox":[185,234,81.5,20.5],"area":1670.75,"segmentation":[],"iscrowd":0},{"id":402,"image_id":174,"category_id":1,"bbox":[258,316,55.5,78.5],"area":4356.75,"segmentation":[],"iscrowd":0},{"id":403,"image_id":175,"category_id":2,"bbox":[71,123,301.5,225],"area":67837.5,"segmentation":[],"iscrowd":0},{"id":404,"image_id":176,"category_id":2,"bbox":[118,153,214.5,161],"area":34534.5,"segmentation":[],"iscrowd":0},{"id":405,"image_id":177,"category_id":2,"bbox":[113,139,202,151.5],"area":30603,"segmentation":[],"iscrowd":0},{"id":406,"image_id":178,"category_id":4,"bbox":[110,77,228.5,245.5],"area":56096.75,"segmentation":[],"iscrowd":0},{"id":407,"image_id":178,"category_id":4,"bbox":[224,84,5,24.5],"area":122.5,"segmentation":[],"iscrowd":0},{"id":408,"image_id":178,"category_id":4,"bbox":[215,87,10,17.5],"area":175,"segmentation":[],"iscrowd":0},{"id":409,"image_id":179,"category_id":3,"bbox":[175,120,95.5,92.5],"area":8833.75,"segmentation":[],"iscrowd":0},{"id":410,"image_id":180,"category_id":1,"bbox":[137,39,196,266],"area":52136,"segmentation":[],"iscrowd":0},{"id":411,"image_id":180,"category_id":1,"bbox":[195,274,97,75],"area":7275,"segmentation":[],"iscrowd":0},{"id":412,"image_id":180,"category_id":1,"bbox":[227,177,80.5,28],"area":2254,"segmentation":[],"iscrowd":0},{"id":413,"image_id":181,"category_id":4,"bbox":[87,51,236.5,215],"area":50847.5,"segmentation":[],"iscrowd":0},{"id":414,"image_id":181,"category_id":4,"bbox":[193,50,14,40.5],"area":567,"segmentation":[],"iscrowd":0},{"id":415,"image_id":182,"category_id":3,"bbox":[184,128,146,139],"area":20294,"segmentation":[],"iscrowd":0},{"id":416,"image_id":183,"category_id":3,"bbox":[160,100,123.5,144],"area":17784,"segmentation":[],"iscrowd":0},{"id":417,"image_id":184,"category_id":1,"bbox":[109,3,229,298.5],"area":68356.5,"segmentation":[],"iscrowd":0},{"id":418,"image_id":184,"category_id":1,"bbox":[208,301,61,44.5],"area":2714.5,"segmentation":[],"iscrowd":0},{"id":419,"image_id":185,"category_id":4,"bbox":[137,48,203.5,262.5],"area":53418.75,"segmentation":[],"iscrowd":0},{"id":420,"image_id":185,"category_id":4,"bbox":[283,35,34,83.5],"area":2839,"segmentation":[],"iscrowd":0},{"id":421,"image_id":186,"category_id":2,"bbox":[66,92,294.5,217.5],"area":64053.75,"segmentation":[],"iscrowd":0},{"id":422,"image_id":187,"category_id":4,"bbox":[125,40,218.5,279.5],"area":61070.75,"segmentation":[],"iscrowd":0},{"id":423,"image_id":187,"category_id":4,"bbox":[245,19,56.5,74],"area":4181,"segmentation":[],"iscrowd":0},{"id":424,"image_id":187,"category_id":4,"bbox":[158,3,16,51.5],"area":824,"segmentation":[],"iscrowd":0},{"id":425,"image_id":188,"category_id":4,"bbox":[117,65,232.5,276],"area":64170,"segmentation":[],"iscrowd":0},{"id":426,"image_id":188,"category_id":4,"bbox":[278,37,40,85],"area":3400,"segmentation":[],"iscrowd":0},{"id":427,"image_id":188,"category_id":4,"bbox":[182,40,55.5,79],"area":4384.5,"segmentation":[],"iscrowd":0},{"id":428,"image_id":189,"category_id":3,"bbox":[133,122,116,113.5],"area":13166,"segmentation":[],"iscrowd":0},{"id":429,"image_id":190,"category_id":1,"bbox":[158,52,200.5,345.5],"area":69272.75,"segmentation":[],"iscrowd":0},{"id":430,"image_id":190,"category_id":1,"bbox":[283,266,82,48],"area":3936,"segmentation":[],"iscrowd":0},{"id":431,"image_id":191,"category_id":4,"bbox":[88,67,236.5,161.5],"area":38194.75,"segmentation":[],"iscrowd":0},{"id":432,"image_id":191,"category_id":4,"bbox":[159,237,92.5,49.5],"area":4578.75,"segmentation":[],"iscrowd":0},{"id":433,"image_id":192,"category_id":3,"bbox":[160,115,100,122.5],"area":12250,"segmentation":[],"iscrowd":0},{"id":434,"image_id":193,"category_id":4,"bbox":[137,37,44,49.5],"area":2178,"segmentation":[],"iscrowd":0},{"id":435,"image_id":193,"category_id":4,"bbox":[255,43,13,44.5],"area":578.5,"segmentation":[],"iscrowd":0},{"id":436,"image_id":193,"category_id":4,"bbox":[303,48,44.5,43],"area":1913.5,"segmentation":[],"iscrowd":0},{"id":437,"image_id":193,"category_id":4,"bbox":[160,100,129.5,87.5],"area":11331.25,"segmentation":[],"iscrowd":0},{"id":438,"image_id":193,"category_id":4,"bbox":[193,195,93,23],"area":2139,"segmentation":[],"iscrowd":0},{"id":439,"image_id":194,"category_id":1,"bbox":[161,19,161,362.5],"area":58362.5,"segmentation":[],"iscrowd":0},{"id":440,"image_id":194,"category_id":1,"bbox":[246,177,64,26],"area":1664,"segmentation":[],"iscrowd":0},{"id":441,"image_id":194,"category_id":1,"bbox":[284,255,81.5,72],"area":5868,"segmentation":[],"iscrowd":0},{"id":442,"image_id":195,"category_id":4,"bbox":[130,42,209,257],"area":53713,"segmentation":[],"iscrowd":0},{"id":443,"image_id":195,"category_id":4,"bbox":[311,34,44.5,120.5],"area":5362.25,"segmentation":[],"iscrowd":0},{"id":444,"image_id":195,"category_id":4,"bbox":[215,41,14.5,62],"area":899,"segmentation":[],"iscrowd":0},{"id":445,"image_id":195,"category_id":4,"bbox":[241,51,9.5,12],"area":114,"segmentation":[],"iscrowd":0},{"id":446,"image_id":196,"category_id":4,"bbox":[112,36,190.5,277],"area":52768.5,"segmentation":[],"iscrowd":0},{"id":447,"image_id":196,"category_id":4,"bbox":[234,31,48.5,86.5],"area":4195.25,"segmentation":[],"iscrowd":0},{"id":448,"image_id":196,"category_id":4,"bbox":[281,143,25,119.5],"area":2987.5,"segmentation":[],"iscrowd":0},{"id":449,"image_id":196,"category_id":4,"bbox":[157,253,42.5,16],"area":680,"segmentation":[],"iscrowd":0},{"id":450,"image_id":197,"category_id":1,"bbox":[102,82,214.5,294.5],"area":63170.25,"segmentation":[],"iscrowd":0},{"id":451,"image_id":197,"category_id":1,"bbox":[179,206,73.5,14.5],"area":1065.75,"segmentation":[],"iscrowd":0},{"id":452,"image_id":197,"category_id":1,"bbox":[218,267,79.5,85.5],"area":6797.25,"segmentation":[],"iscrowd":0},{"id":453,"image_id":198,"category_id":4,"bbox":[120,28,246,302.5],"area":74415,"segmentation":[],"iscrowd":0},{"id":454,"image_id":198,"category_id":4,"bbox":[256,38,69.5,84.5],"area":5872.75,"segmentation":[],"iscrowd":0},{"id":455,"image_id":198,"category_id":4,"bbox":[261,138,83,33.5],"area":2780.5,"segmentation":[],"iscrowd":0},{"id":456,"image_id":199,"category_id":2,"bbox":[109,120,214.5,159],"area":34105.5,"segmentation":[],"iscrowd":0},{"id":457,"image_id":200,"category_id":1,"bbox":[81,14,230,355],"area":81650,"segmentation":[],"iscrowd":0},{"id":458,"image_id":201,"category_id":4,"bbox":[130,123,231.5,234.5],"area":54286.75,"segmentation":[],"iscrowd":0},{"id":459,"image_id":201,"category_id":4,"bbox":[240,94,19.5,46.5],"area":906.75,"segmentation":[],"iscrowd":0},{"id":460,"image_id":201,"category_id":4,"bbox":[315,98,22.5,56],"area":1260,"segmentation":[],"iscrowd":0},{"id":461,"image_id":202,"category_id":1,"bbox":[120,73,209,264.5],"area":55280.5,"segmentation":[],"iscrowd":0},{"id":462,"image_id":202,"category_id":1,"bbox":[188,201,88.5,20],"area":1770,"segmentation":[],"iscrowd":0},{"id":463,"image_id":202,"category_id":1,"bbox":[151,289,94.5,71.5],"area":6756.75,"segmentation":[],"iscrowd":0},{"id":464,"image_id":202,"category_id":1,"bbox":[120,73,191,32.5],"area":6207.5,"segmentation":[],"iscrowd":0},{"id":465,"image_id":203,"category_id":4,"bbox":[105,20,236.5,317],"area":74970.5,"segmentation":[],"iscrowd":0},{"id":466,"image_id":203,"category_id":4,"bbox":[236,25,71,92],"area":6532,"segmentation":[],"iscrowd":0},{"id":467,"image_id":203,"category_id":4,"bbox":[174,241,105.5,52],"area":5486,"segmentation":[],"iscrowd":0},{"id":468,"image_id":204,"category_id":2,"bbox":[152,95,201,149],"area":29949,"segmentation":[],"iscrowd":0},{"id":469,"image_id":205,"category_id":1,"bbox":[91,90,213.5,278.5],"area":59459.75,"segmentation":[],"iscrowd":0},{"id":470,"image_id":205,"category_id":1,"bbox":[160,209,69.5,19],"area":1320.5,"segmentation":[],"iscrowd":0},{"id":471,"image_id":205,"category_id":1,"bbox":[215,278,52.5,87.5],"area":4593.75,"segmentation":[],"iscrowd":0},{"id":472,"image_id":205,"category_id":1,"bbox":[235,283,27.5,15],"area":412.5,"segmentation":[],"iscrowd":0}]}